{
    "extra": {
        "fatal_item_ids": [],
        "logid": "2025012817342557A716FA7108B4677ED2",
        "now": 1738085667000
    },
    "hasMore": true,
    "itemList": [
        {
            "AIGCDescription": "",
            "BAInfo": "",
            "CategoryType": 120,
            "adAuthorization": false,
            "adLabelVersion": 0,
            "aigcLabelType": 0,
            "anchors": [
                {
                    "description": "CapCut \u00ac\u2211 Video Editor",
                    "extraInfo": {
                        "subtype": ""
                    },
                    "icon": {
                        "urlList": [
                            "https://p77-sg.tiktokcdn.com/obj/tiktok-obj/capcut_logo_64px_bk.png?shp=b59d6b55&shcp=-"
                        ]
                    },
                    "id": "0",
                    "keyword": "CapCut \u00ac\u2211 Try this template",
                    "logExtra": "{\"anchor_id\":0,\"anchor_name\":\"CapCut \u00ac\u2211 Try this template\",\"anchor_name_type\":\"template_0\",\"anchor_title_detail\":\"None\",\"anchor_type\":\"TT_CAPCUT\",\"capability_key\":\"none\",\"cc_template_pay_type\":0,\"if_device_language\":\"none\",\"if_race_trigger\":0,\"is_two_line\":0,\"maker_source\":\"\",\"template_id\":\"7416518336122539320\",\"tutorial_id\":\"none\",\"viamaker_anchor_capability_key_weight\":1,\"viamaker_anchor_style_idx\":-1,\"viamaker_anchor_style_source\":3,\"video_source\":0,\"video_type_id\":2}",
                    "schema": "https://www.capcut.com/editor-template?scenario=tiktok&utm_campaign=71351105&utm_content=7416518336122539320&utm_medium=tiktok_anchor&utm_source=tiktok_anchor_template",
                    "thumbnail": {
                        "height": 64,
                        "urlList": [
                            "https://p77-sg.tiktokcdn.com/obj/tiktok-obj/64x_Capcut3x.png?shp=b59d6b55&shcp=-"
                        ],
                        "width": 64
                    },
                    "type": 54
                }
            ],
            "author": {
                "avatarLarger": "https://p16-sign-va.tiktokcdn.com/tos-maliva-avt-0068/29277cb96951be8fbf0b761276078b41~c5_1080x1080.jpeg?lk3s=a5d48078&nonce=30039&refresh_token=c47e932d50939d9e0d1d64614ccc4ef2&x-expires=1738256400&x-signature=NOCUbTybYx628d0iw71BSVQt%2FHs%3D&shp=a5d48078&shcp=b59d6b55",
                "avatarMedium": "https://p16-sign-va.tiktokcdn.com/tos-maliva-avt-0068/29277cb96951be8fbf0b761276078b41~c5_720x720.jpeg?lk3s=a5d48078&nonce=64455&refresh_token=ca75404ff859ba8fddc159a050638a9d&x-expires=1738256400&x-signature=z5GNi%2B3nIsZWyjehEWaIRk4Y%2FPA%3D&shp=a5d48078&shcp=b59d6b55",
                "avatarThumb": "https://p16-sign-va.tiktokcdn.com/tos-maliva-avt-0068/29277cb96951be8fbf0b761276078b41~c5_100x100.jpeg?lk3s=a5d48078&nonce=74669&refresh_token=af37c0bbd2d1b742e9cccdedad693df7&x-expires=1738256400&x-signature=jq8njHmK6g9dEnbqfcEr5o6rSf4%3D&shp=a5d48078&shcp=b59d6b55",
                "commentSetting": 0,
                "downloadSetting": 0,
                "duetSetting": 0,
                "ftc": false,
                "id": "6680421507174663174",
                "isADVirtual": false,
                "isEmbedBanned": false,
                "nickname": "\u00ff\u03c0\u00ff\u00a5\u00ff\u00df\u0178\u00c7 \u00ff\u00df\u0178\u00d1\u00ff\u00df\u00ff\u2211\u0178\u00c5\u00ff\u00df\u0178\u00d1 \uf8ff\u00fc\u00f2\u00e7\uf8ff\u00fc\u00ed\u00f9",
                "openFavorite": false,
                "privateAccount": false,
                "relation": 0,
                "secUid": "MS4wLjABAAAA_CMCDG1Yk5hUk1Bh2EEEhqlvi_6KlOP4Rfl4VRN2fJcezFnW1d4ZJjqeoeUFombd",
                "secret": false,
                "signature": "\u0178\u00dc\u00ff\u2260\u00ff\u00df\u0178\u00e0\u0178\u00d1 \u00ff\u00df\u0178\u00dc \u0178\u00dc\u0178\u00c7\u00ff\u00d8\u0178\u00d6 \u0178\u00d6\u00ff\u2260\u00ff\u2122\u0178\u00e0\u0178\u00e2 \u0178\u00e4\u0178\u00c9\u0178\u00e0\u0178\u00dc \u00ff\u03c0\u0178\u00dc\u00ff\u00d8 \u00ff\u2260\u00ff\u2265\u0178\u00dc \u00ff\u220f\u0178\u00dc \u0178\u00d6\u00ff\u2122\u00ff\u00df\u00ff\u00ae\u00ff\u03c0\u0178\u00e4\u0178\u00dc\u00ff\u00df\n \u00ff\u00df\u00ff\u00d8\u00ff\u03c0\u0178\u00d6\u0178\u00e0\u0178\u00dc\u00ff\u00df \u0178\u00c9\u0178\u00e4 \u0178\u00dc\u0178\u00c7\u00ff\u00d8\u0178\u00d6 \u00ff\u00df\u0178\u00d1\u0178\u00d6\u00ff\u2264\u0178\u00e4\u00ff\u00d8 \n\u201a\u00a8\u00e1\u00d4\u220f\u00e8\u00ff\u00df\u0178\u00dc\u00ff\u2265\u00ff\u2122\u00ff\u00df\u201a\u00a8\u00e1\u00d4\u220f\u00e8",
                "stitchSetting": 0,
                "ttSeller": false,
                "uniqueId": "baby......03",
                "verified": false
            },
            "authorStats": {
                "diggCount": 7050,
                "followerCount": 834000,
                "followingCount": 21,
                "friendCount": 0,
                "heart": 11700000,
                "heartCount": 11700000,
                "videoCount": 2863
            },
            "backendSourceEventTracking": "fyp_32",
            "challenges": [
                {
                    "coverLarger": "",
                    "coverMedium": "",
                    "coverThumb": "",
                    "desc": "",
                    "id": "29773070",
                    "isCommerce": false,
                    "profileLarger": "",
                    "profileMedium": "",
                    "profileThumb": "",
                    "stats": {
                        "videoCount": 0,
                        "viewCount": 0
                    },
                    "title": "\u0178\u00d6\u00ff\u00a5\u00ff\u00df\u00ff\u00b0\u00ff\u00df\u0178\u00d1\u0178\u00d1\u0178\u00e1"
                },
                {
                    "coverLarger": "",
                    "coverMedium": "",
                    "coverThumb": "",
                    "desc": "",
                    "id": "1671568001942534",
                    "isCommerce": false,
                    "profileLarger": "",
                    "profileMedium": "",
                    "profileThumb": "",
                    "stats": {
                        "videoCount": 0,
                        "viewCount": 0
                    },
                    "title": "\u00ff\u00df\u20ac\u00e5\u0178\u00dc\u201a\u00f4\u00b0\u00ff\u00df\u0178\u00dc\u00ff\u2122\u0178\u00d6_\u00ff\u03c0\u00ff\u00a5\u00ff\u00df\u0178\u00c7_\u00ff\u00df\u0178\u00d1\u00ff\u2211\u0178\u00c5\u00ff\u00df\u0178\u00d1\u201a\u00f9\u00a7\uf8ff\u00fc\u00a7\u00a7"
                },
                {
                    "coverLarger": "",
                    "coverMedium": "",
                    "coverThumb": "",
                    "desc": "",
                    "id": "7005655906037792773",
                    "isCommerce": false,
                    "profileLarger": "",
                    "profileMedium": "",
                    "profileThumb": "",
                    "stats": {
                        "videoCount": 0,
                        "viewCount": 0
                    },
                    "title": "\u00ff\u2122\u00ff\u00ae\u00ff\u03c0\u0178\u00e0\u0178\u00dc\u0178\u00e4_\u00ff\u03c0\u0178\u00d1\u0178\u00e4_\u00ff\u00df\u0178\u00dc\u00ff\u2265\u00ff\u2122\u00ff\u222b\u00ff\u00b1\u00ff\u00df\u0178\u00d6"
                },
                {
                    "coverLarger": "https://p77-sg.tiktokcdn.com/obj/tiktok-obj/1617014536729602.JPEG?shp=b59d6b55&shcp=-",
                    "coverMedium": "https://p77-sg.tiktokcdn.com/obj/tiktok-obj/1617014536729602.JPEG?shp=b59d6b55&shcp=-",
                    "coverThumb": "https://p77-sg.tiktokcdn.com/obj/tiktok-obj/1617014536729602.JPEG?shp=b59d6b55&shcp=-",
                    "desc": "",
                    "id": "5850",
                    "isCommerce": false,
                    "profileLarger": "https://p77-sg.tiktokcdn.com/obj/tiktok-obj/1617014531310594.JPEG?shp=b59d6b55&shcp=-",
                    "profileMedium": "https://p77-sg.tiktokcdn.com/obj/tiktok-obj/1617014531310594.JPEG?shp=b59d6b55&shcp=-",
                    "profileThumb": "https://p77-sg.tiktokcdn.com/obj/tiktok-obj/1617014531310594.JPEG?shp=b59d6b55&shcp=-",
                    "stats": {
                        "videoCount": 0,
                        "viewCount": 0
                    },
                    "title": "baby"
                },
                {
                    "coverLarger": "",
                    "coverMedium": "",
                    "coverThumb": "",
                    "desc": "CapCut is a new, easy-to-use video editing tool designed for mobile platforms. CapCut provides users with a wide range of video editing functions, filters, audio &amp; visual effects, video templates, while keeping it free of charge and ads-free. Everyone can be a creator by using CapCut.  \n\nStart creating your cool videos today: \nhttps://capcut.onelink.me/XKqI/228cad85",
                    "id": "1663935709411330",
                    "isCommerce": false,
                    "profileLarger": "https://p77-sg.tiktokcdn.com/obj/tiktok-obj/1d1c20b6de3fc0b4da37670699cbcb07?shp=b59d6b55&shcp=-",
                    "profileMedium": "https://p77-sg.tiktokcdn.com/obj/tiktok-obj/1d1c20b6de3fc0b4da37670699cbcb07?shp=b59d6b55&shcp=-",
                    "profileThumb": "https://p77-sg.tiktokcdn.com/obj/tiktok-obj/1d1c20b6de3fc0b4da37670699cbcb07?shp=b59d6b55&shcp=-",
                    "stats": {
                        "videoCount": 0,
                        "viewCount": 0
                    },
                    "title": "capcut"
                }
            ],
            "collected": false,
            "contents": [
                {
                    "desc": "#\u0178\u00d6\u00ff\u00a5\u00ff\u00df\u00ff\u00b0\u00ff\u00df\u0178\u00d1\u0178\u00d1\u0178\u00e1 #\u00ff\u00df\u20ac\u00e5\u0178\u00dc\u201a\u00f4\u00b0\u00ff\u00df\u0178\u00dc\u00ff\u2122\u0178\u00d6_\u00ff\u03c0\u00ff\u00a5\u00ff\u00df\u0178\u00c7_\u00ff\u00df\u0178\u00d1\u00ff\u2211\u0178\u00c5\u00ff\u00df\u0178\u00d1\u201a\u00f9\u00a7\uf8ff\u00fc\u00a7\u00a7 #\u00ff\u2122\u00ff\u00ae\u00ff\u03c0\u0178\u00e0\u0178\u00dc\u0178\u00e4_\u00ff\u03c0\u0178\u00d1\u0178\u00e4_\u00ff\u00df\u0178\u00dc\u00ff\u2265\u00ff\u2122\u00ff\u222b\u00ff\u00b1\u00ff\u00df\u0178\u00d6 #baby #CapCut ",
                    "textExtra": [
                        {
                            "awemeId": "",
                            "end": 9,
                            "hashtagId": "29773070",
                            "hashtagName": "\u0178\u00d6\u00ff\u00a5\u00ff\u00df\u00ff\u00b0\u00ff\u00df\u0178\u00d1\u0178\u00d1\u0178\u00e1",
                            "isCommerce": false,
                            "secUid": "",
                            "start": 0,
                            "subType": 0,
                            "type": 1,
                            "userId": "",
                            "userUniqueId": ""
                        },
                        {
                            "awemeId": "",
                            "end": 34,
                            "hashtagId": "1671568001942534",
                            "hashtagName": "\u00ff\u00df\u20ac\u00e5\u0178\u00dc\u201a\u00f4\u00b0\u00ff\u00df\u0178\u00dc\u00ff\u2122\u0178\u00d6_\u00ff\u03c0\u00ff\u00a5\u00ff\u00df\u0178\u00c7_\u00ff\u00df\u0178\u00d1\u00ff\u2211\u0178\u00c5\u00ff\u00df\u0178\u00d1\u201a\u00f9\u00a7\uf8ff\u00fc\u00a7\u00a7",
                            "isCommerce": false,
                            "secUid": "",
                            "start": 10,
                            "subType": 0,
                            "type": 1,
                            "userId": "",
                            "userUniqueId": ""
                        },
                        {
                            "awemeId": "",
                            "end": 55,
                            "hashtagId": "7005655906037792773",
                            "hashtagName": "\u00ff\u2122\u00ff\u00ae\u00ff\u03c0\u0178\u00e0\u0178\u00dc\u0178\u00e4_\u00ff\u03c0\u0178\u00d1\u0178\u00e4_\u00ff\u00df\u0178\u00dc\u00ff\u2265\u00ff\u2122\u00ff\u222b\u00ff\u00b1\u00ff\u00df\u0178\u00d6",
                            "isCommerce": false,
                            "secUid": "",
                            "start": 35,
                            "subType": 0,
                            "type": 1,
                            "userId": "",
                            "userUniqueId": ""
                        },
                        {
                            "awemeId": "",
                            "end": 61,
                            "hashtagId": "5850",
                            "hashtagName": "baby",
                            "isCommerce": false,
                            "secUid": "",
                            "start": 56,
                            "subType": 0,
                            "type": 1,
                            "userId": "",
                            "userUniqueId": ""
                        },
                        {
                            "awemeId": "",
                            "end": 69,
                            "hashtagId": "1663935709411330",
                            "hashtagName": "capcut",
                            "isCommerce": false,
                            "secUid": "",
                            "start": 62,
                            "subType": 0,
                            "type": 1,
                            "userId": "",
                            "userUniqueId": ""
                        }
                    ]
                }
            ],
            "createTime": 1730402223,
            "desc": "#\u0178\u00d6\u00ff\u00a5\u00ff\u00df\u00ff\u00b0\u00ff\u00df\u0178\u00d1\u0178\u00d1\u0178\u00e1 #\u00ff\u00df\u20ac\u00e5\u0178\u00dc\u201a\u00f4\u00b0\u00ff\u00df\u0178\u00dc\u00ff\u2122\u0178\u00d6_\u00ff\u03c0\u00ff\u00a5\u00ff\u00df\u0178\u00c7_\u00ff\u00df\u0178\u00d1\u00ff\u2211\u0178\u00c5\u00ff\u00df\u0178\u00d1\u201a\u00f9\u00a7\uf8ff\u00fc\u00a7\u00a7 #\u00ff\u2122\u00ff\u00ae\u00ff\u03c0\u0178\u00e0\u0178\u00dc\u0178\u00e4_\u00ff\u03c0\u0178\u00d1\u0178\u00e4_\u00ff\u00df\u0178\u00dc\u00ff\u2265\u00ff\u2122\u00ff\u222b\u00ff\u00b1\u00ff\u00df\u0178\u00d6 #baby #CapCut ",
            "digged": false,
            "diversificationId": 10017,
            "duetDisplay": 0,
            "duetEnabled": true,
            "duetInfo": {
                "duetFromId": "0"
            },
            "forFriend": false,
            "id": "7432020938117369094",
            "isAd": false,
            "itemCommentStatus": 0,
            "itemMute": false,
            "item_control": {
                "can_repost": true
            },
            "music": {
                "album": "",
                "authorName": ".\u00ff\u00a5\u0178\u00c4\u0178\u00c4\u0178\u00c4\u201a\u00eb\u00d6\u201a\u00c9\u00f9\uf8ff\u00fc\u00e9\u2202\u00ff\u2264\u0178\u00d6\u0178\u00c4\u00ff\u00df\u0178\u00dc\u0178\u00e4\uf8ff\u00f9\u00d1\u00fb\u0178\u00c4\u0178\u00c4\u00ff\u00df\u201a\u00eb\u00d6\u201a\u00c9\u00f9\u0178\u00d6\u00ff\u00c6",
                "coverLarge": "https://p16-sign-sg.tiktokcdn.com/aweme/1080x1080/tos-alisg-avt-0068/5f75faa970b936c9b0e691f89cfe83d1.jpeg?lk3s=a5d48078&nonce=19040&refresh_token=1f18a6a702b4debf87538c63455efe9d&x-expires=1738256400&x-signature=gCjhJxN2AZ2Y8XfXe45yXdihoP8%3D&shp=a5d48078&shcp=b59d6b55",
                "coverMedium": "https://p16-sign-sg.tiktokcdn.com/aweme/720x720/tos-alisg-avt-0068/5f75faa970b936c9b0e691f89cfe83d1.jpeg?lk3s=a5d48078&nonce=46811&refresh_token=d28e5dd4355d24f910feadceaea04b69&x-expires=1738256400&x-signature=PEPEfg5ftq13tuVCnV5XGLTPjtQ%3D&shp=a5d48078&shcp=b59d6b55",
                "coverThumb": "https://p16-sign-sg.tiktokcdn.com/aweme/100x100/tos-alisg-avt-0068/5f75faa970b936c9b0e691f89cfe83d1.jpeg?lk3s=a5d48078&nonce=11907&refresh_token=38ee66b975de56289a1c60c5b3d19085&x-expires=1738256400&x-signature=nS3myirr5jYKwUiSBSWN6cKfKGo%3D&shp=a5d48078&shcp=b59d6b55",
                "duration": 28,
                "id": "7416522821200808720",
                "isCopyrighted": false,
                "original": true,
                "playUrl": "https://v77.tiktokcdn-eu.com/ce5c37f05a9bdb75078abee76bf78e3d/679a66bf/video/tos/alisg/tos-alisg-v-27dcd7/ooAseEG2OyfDDLTNNerxBNgoAQ2sCDsYtoDZIz/?a=1233&bti=NDU3ZjAwOg%3D%3D&ch=0&cr=0&dr=0&er=2&cd=0%7C0%7C0%7C0&br=250&bt=125&ft=.NpOcInz7ThF3nLOXq8Zmo&mime_type=audio_mpeg&qs=6&rc=aTg5OThmNmU0PDk2aGRnNEBpam91amo5cmhmdTMzODU8NEAzYWNgYjNeXzQxNi5iYWM0YSNnZ2BzMmQ0ZGpgLS1kMS1zcw%3D%3D&vvpl=1&l=2025012817342557A716FA7108B4677ED2&btag=e000b8000&download=true",
                "title": "\u00ff\u00df\u0178\u00d1\u00ff\u00b5\u0178\u00e0\u00ff\u2122 \u00ff\u00df\u0178\u00d1\u00ff\u00a3\u00ff\u00b5\u0178\u00d1\u0178\u00e4"
            },
            "officalItem": false,
            "originalItem": false,
            "playlistId": "",
            "privateItem": false,
            "secret": false,
            "shareEnabled": true,
            "showNotPass": false,
            "stats": {
                "collectCount": 407,
                "commentCount": 42,
                "diggCount": 3330,
                "playCount": 118300,
                "shareCount": 184
            },
            "statsV2": {
                "collectCount": "407",
                "commentCount": "42",
                "diggCount": "3330",
                "playCount": "118250",
                "repostCount": "0",
                "shareCount": "184"
            },
            "stitchDisplay": 0,
            "stitchEnabled": true,
            "textExtra": [
                {
                    "awemeId": "",
                    "end": 9,
                    "hashtagId": "29773070",
                    "hashtagName": "\u0178\u00d6\u00ff\u00a5\u00ff\u00df\u00ff\u00b0\u00ff\u00df\u0178\u00d1\u0178\u00d1\u0178\u00e1",
                    "isCommerce": false,
                    "secUid": "",
                    "start": 0,
                    "subType": 0,
                    "type": 1,
                    "userId": "",
                    "userUniqueId": ""
                },
                {
                    "awemeId": "",
                    "end": 34,
                    "hashtagId": "1671568001942534",
                    "hashtagName": "\u00ff\u00df\u20ac\u00e5\u0178\u00dc\u201a\u00f4\u00b0\u00ff\u00df\u0178\u00dc\u00ff\u2122\u0178\u00d6_\u00ff\u03c0\u00ff\u00a5\u00ff\u00df\u0178\u00c7_\u00ff\u00df\u0178\u00d1\u00ff\u2211\u0178\u00c5\u00ff\u00df\u0178\u00d1\u201a\u00f9\u00a7\uf8ff\u00fc\u00a7\u00a7",
                    "isCommerce": false,
                    "secUid": "",
                    "start": 10,
                    "subType": 0,
                    "type": 1,
                    "userId": "",
                    "userUniqueId": ""
                },
                {
                    "awemeId": "",
                    "end": 55,
                    "hashtagId": "7005655906037792773",
                    "hashtagName": "\u00ff\u2122\u00ff\u00ae\u00ff\u03c0\u0178\u00e0\u0178\u00dc\u0178\u00e4_\u00ff\u03c0\u0178\u00d1\u0178\u00e4_\u00ff\u00df\u0178\u00dc\u00ff\u2265\u00ff\u2122\u00ff\u222b\u00ff\u00b1\u00ff\u00df\u0178\u00d6",
                    "isCommerce": false,
                    "secUid": "",
                    "start": 35,
                    "subType": 0,
                    "type": 1,
                    "userId": "",
                    "userUniqueId": ""
                },
                {
                    "awemeId": "",
                    "end": 61,
                    "hashtagId": "5850",
                    "hashtagName": "baby",
                    "isCommerce": false,
                    "secUid": "",
                    "start": 56,
                    "subType": 0,
                    "type": 1,
                    "userId": "",
                    "userUniqueId": ""
                },
                {
                    "awemeId": "",
                    "end": 69,
                    "hashtagId": "1663935709411330",
                    "hashtagName": "capcut",
                    "isCommerce": false,
                    "secUid": "",
                    "start": 62,
                    "subType": 0,
                    "type": 1,
                    "userId": "",
                    "userUniqueId": ""
                }
            ],
            "textLanguage": "un",
            "textTranslatable": false,
            "video": {
                "VQScore": "67.57",
                "bitrate": 439723,
                "bitrateInfo": [
                    {
                        "Bitrate": 439723,
                        "CodecType": "h264",
                        "GearName": "lower_540_0",
                        "MVMAF": "\"\"",
                        "PlayAddr": {
                            "DataSize": 1745976,
                            "FileCs": "c:0-21834-e37a",
                            "FileHash": "9006ed5f22c89b259a139e3c94518cec",
                            "Height": 1024,
                            "Uri": "v09044g40000cshtbg7og65hdjkshr3g",
                            "UrlKey": "v09044g40000cshtbg7og65hdjkshr3g_h264_540p_439723",
                            "UrlList": [
                                "https://v16-webapp-prime.tiktok.com/video/tos/alisg/tos-alisg-pve-0037c001/ogkByBAQHniBDExOEcQWwqj7ZjIPIUV7P1iSb/?a=1988&bti=NDU3ZjAwOg%3D%3D&ch=0&cr=3&dr=0&lr=all&cd=0%7C0%7C0%7C&cv=1&br=858&bt=429&cs=0&ds=6&ft=4fUEKMRh8Zmo0TM83b4jVcUerpWrKsd.&mime_type=video_mp4&qs=4&rc=aWRlZ2U5OWZoOzM8aDo8OkBpanV2bWs5cmp3djMzNzczM0BiNjU2XmE1X2IxNWJiYS4yYSMwZWhhMmQ0X2VgLS1kMTZzcw%3D%3D&btag=e00088000&expire=1738258498&l=2025012817342557A716FA7108B4677ED2&ply_type=2&policy=2&signature=f652a8a0139232fd9bb91b10bc364add&tk=tt_chain_token",
                                "https://v19-webapp-prime.tiktok.com/video/tos/alisg/tos-alisg-pve-0037c001/ogkByBAQHniBDExOEcQWwqj7ZjIPIUV7P1iSb/?a=1988&bti=NDU3ZjAwOg%3D%3D&ch=0&cr=3&dr=0&lr=all&cd=0%7C0%7C0%7C&cv=1&br=858&bt=429&cs=0&ds=6&ft=4fUEKMRh8Zmo0TM83b4jVcUerpWrKsd.&mime_type=video_mp4&qs=4&rc=aWRlZ2U5OWZoOzM8aDo8OkBpanV2bWs5cmp3djMzNzczM0BiNjU2XmE1X2IxNWJiYS4yYSMwZWhhMmQ0X2VgLS1kMTZzcw%3D%3D&btag=e00088000&expire=1738258498&l=2025012817342557A716FA7108B4677ED2&ply_type=2&policy=2&signature=f652a8a0139232fd9bb91b10bc364add&tk=tt_chain_token",
                                "https://www.tiktok.com/aweme/v1/play/?faid=1988&file_id=5719d7eee98048eebc86d6ab9d8b9aef&is_play_url=1&item_id=7432020938117369094&line=0&ply_type=2&signaturev3=dmlkZW9faWQ7ZmlsZV9pZDtpdGVtX2lkLjY1YmU4ZDRlOTdhNjBiZjNhMTAwMzk3OGNhNGNjMzZk&tk=tt_chain_token&video_id=v09044g40000cshtbg7og65hdjkshr3g"
                            ],
                            "Width": 576
                        },
                        "QualityType": 24
                    },
                    {
                        "Bitrate": 326237,
                        "CodecType": "h264",
                        "GearName": "lowest_540_0",
                        "MVMAF": "\"\"",
                        "PlayAddr": {
                            "DataSize": 1295367,
                            "FileCs": "c:0-21802-c3b2",
                            "FileHash": "dbd7270746f9e55c8f9aeb210142655f",
                            "Height": 1024,
                            "Uri": "v09044g40000cshtbg7og65hdjkshr3g",
                            "UrlKey": "v09044g40000cshtbg7og65hdjkshr3g_h264_540p_326237",
                            "UrlList": [
                                "https://v16-webapp-prime.tiktok.com/video/tos/useast2a/tos-useast2a-ve-0068c003/o4EQBHaPVAQixnPEZwP3yBbj1SiII7BU7EKOw/?a=1988&bti=NDU3ZjAwOg%3D%3D&ch=0&cr=3&dr=0&lr=all&cd=0%7C0%7C0%7C&cv=1&br=636&bt=318&cs=0&ds=6&ft=4fUEKMRh8Zmo0TM83b4jVcUerpWrKsd.&mime_type=video_mp4&qs=5&rc=NDs4OmU8MzQ5OGQ4PDQ1aUBpanV2bWs5cmp3djMzNzczM0A2NmIwLzJiNjAxYl5iLTNjYSMwZWhhMmQ0X2VgLS1kMTZzcw%3D%3D&btag=e00088000&expire=1738258498&l=2025012817342557A716FA7108B4677ED2&ply_type=2&policy=2&signature=896ebc9f37c87516c73069e7906e0382&tk=tt_chain_token",
                                "https://v19-webapp-prime.tiktok.com/video/tos/useast2a/tos-useast2a-ve-0068c003/o4EQBHaPVAQixnPEZwP3yBbj1SiII7BU7EKOw/?a=1988&bti=NDU3ZjAwOg%3D%3D&ch=0&cr=3&dr=0&lr=all&cd=0%7C0%7C0%7C&cv=1&br=636&bt=318&cs=0&ds=6&ft=4fUEKMRh8Zmo0TM83b4jVcUerpWrKsd.&mime_type=video_mp4&qs=5&rc=NDs4OmU8MzQ5OGQ4PDQ1aUBpanV2bWs5cmp3djMzNzczM0A2NmIwLzJiNjAxYl5iLTNjYSMwZWhhMmQ0X2VgLS1kMTZzcw%3D%3D&btag=e00088000&expire=1738258498&l=2025012817342557A716FA7108B4677ED2&ply_type=2&policy=2&signature=896ebc9f37c87516c73069e7906e0382&tk=tt_chain_token",
                                "https://www.tiktok.com/aweme/v1/play/?faid=1988&file_id=ff6201e9a5ea453691e0592b37e59891&is_play_url=1&item_id=7432020938117369094&line=0&ply_type=2&signaturev3=dmlkZW9faWQ7ZmlsZV9pZDtpdGVtX2lkLjU1ZTg1Zjc4NmRiOWNlMzZkZGQxYTlhMzE0NTMxNmNi&tk=tt_chain_token&video_id=v09044g40000cshtbg7og65hdjkshr3g"
                            ],
                            "Width": 576
                        },
                        "QualityType": 25
                    },
                    {
                        "Bitrate": 318448,
                        "CodecType": "h265_hvc1",
                        "GearName": "adapt_lower_720_1",
                        "MVMAF": "\"{\\\"v2.0\\\": {\\\"ori\\\": {\\\"v1080\\\": 90.475, \\\"v960\\\": 91.061, \\\"v864\\\": 92.699, \\\"v720\\\": 94.585}, \\\"srv1\\\": {\\\"v1080\\\": 96.537, \\\"v960\\\": 97.895, \\\"v864\\\": 98.481, \\\"v720\\\": 98.819}}}\"",
                        "PlayAddr": {
                            "DataSize": 1264439,
                            "FileCs": "c:0-21417-be3b",
                            "FileHash": "eb51d417aafac64e220dfe7557ea1681",
                            "Height": 1280,
                            "Uri": "v09044g40000cshtbg7og65hdjkshr3g",
                            "UrlKey": "v09044g40000cshtbg7og65hdjkshr3g_bytevc1_720p_318448",
                            "UrlList": [
                                "https://v16-webapp-prime.tiktok.com/video/tos/useast2a/tos-useast2a-ve-0068c002/oAQHIgBaRsOIAVDn2FRwf2fdOXiEAECQJR9NBK/?a=1988&bti=NDU3ZjAwOg%3D%3D&ch=0&cr=3&dr=0&lr=all&cd=0%7C0%7C0%7C&cv=1&br=620&bt=310&cs=2&ds=3&eid=7936&ft=4fUEKMRh8Zmo0TM83b4jVcUerpWrKsd.&mime_type=video_mp4&qs=14&rc=OjQ7aWhoNDZoNjM5N2hnPEBpanV2bWs5cmp3djMzNzczM0AuMTYxNjVhNi8xMS1hMTEtYSMwZWhhMmQ0X2VgLS1kMTZzcw%3D%3D&btag=e00088000&expire=1738258498&l=2025012817342557A716FA7108B4677ED2&ply_type=2&policy=2&signature=3938688307ac85478424c7c35c41b8fc&tk=tt_chain_token",
                                "https://v19-webapp-prime.tiktok.com/video/tos/useast2a/tos-useast2a-ve-0068c002/oAQHIgBaRsOIAVDn2FRwf2fdOXiEAECQJR9NBK/?a=1988&bti=NDU3ZjAwOg%3D%3D&ch=0&cr=3&dr=0&lr=all&cd=0%7C0%7C0%7C&cv=1&br=620&bt=310&cs=2&ds=3&eid=7936&ft=4fUEKMRh8Zmo0TM83b4jVcUerpWrKsd.&mime_type=video_mp4&qs=14&rc=OjQ7aWhoNDZoNjM5N2hnPEBpanV2bWs5cmp3djMzNzczM0AuMTYxNjVhNi8xMS1hMTEtYSMwZWhhMmQ0X2VgLS1kMTZzcw%3D%3D&btag=e00088000&expire=1738258498&l=2025012817342557A716FA7108B4677ED2&ply_type=2&policy=2&signature=3938688307ac85478424c7c35c41b8fc&tk=tt_chain_token",
                                "https://www.tiktok.com/aweme/v1/play/?faid=1988&file_id=094d4ed40640432e93d18e9e4f984117&is_play_url=1&item_id=7432020938117369094&line=0&ply_type=2&signaturev3=dmlkZW9faWQ7ZmlsZV9pZDtpdGVtX2lkLjlmMDc3OGUwOTQ2M2MzMmVmNGJlNmE4YWZlNDI1YmEx&tk=tt_chain_token&video_id=v09044g40000cshtbg7og65hdjkshr3g"
                            ],
                            "Width": 720
                        },
                        "QualityType": 14
                    },
                    {
                        "Bitrate": 227010,
                        "CodecType": "h265_hvc1",
                        "GearName": "adapt_540_1",
                        "MVMAF": "\"{\\\"v2.0\\\": {\\\"ori\\\": {\\\"v1080\\\": 84.218, \\\"v960\\\": 87.954, \\\"v864\\\": 89.21, \\\"v720\\\": 91.76}, \\\"srv1\\\": {\\\"v1080\\\": 95.507, \\\"v960\\\": 96.895, \\\"v864\\\": 97.382, \\\"v720\\\": 97.907}}}\"",
                        "PlayAddr": {
                            "DataSize": 901372,
                            "FileCs": "c:0-21417-2f9b",
                            "FileHash": "fcc10f0bc3b40a9170082dc71323b2f8",
                            "Height": 1024,
                            "Uri": "v09044g40000cshtbg7og65hdjkshr3g",
                            "UrlKey": "v09044g40000cshtbg7og65hdjkshr3g_bytevc1_540p_227010",
                            "UrlList": [
                                "https://v16-webapp-prime.tiktok.com/video/tos/useast2a/tos-useast2a-pve-0068/o4IHjPNEUPcEwxwbSQOiIi8F7BBZIyAnBPVw2/?a=1988&bti=NDU3ZjAwOg%3D%3D&ch=0&cr=3&dr=0&lr=all&cd=0%7C0%7C0%7C&cv=1&br=442&bt=221&cs=2&ds=6&eid=7936&ft=4fUEKMRh8Zmo0TM83b4jVcUerpWrKsd.&mime_type=video_mp4&qs=11&rc=Z2U7NTw3NzVoODg2NDNmN0BpanV2bWs5cmp3djMzNzczM0AuLzNjMV8wXl4xLzFgX2ItYSMwZWhhMmQ0X2VgLS1kMTZzcw%3D%3D&btag=e00088000&expire=1738258498&l=2025012817342557A716FA7108B4677ED2&ply_type=2&policy=2&signature=63b211c124ca63d46a097133936f8c6e&tk=tt_chain_token",
                                "https://v19-webapp-prime.tiktok.com/video/tos/useast2a/tos-useast2a-pve-0068/o4IHjPNEUPcEwxwbSQOiIi8F7BBZIyAnBPVw2/?a=1988&bti=NDU3ZjAwOg%3D%3D&ch=0&cr=3&dr=0&lr=all&cd=0%7C0%7C0%7C&cv=1&br=442&bt=221&cs=2&ds=6&eid=7936&ft=4fUEKMRh8Zmo0TM83b4jVcUerpWrKsd.&mime_type=video_mp4&qs=11&rc=Z2U7NTw3NzVoODg2NDNmN0BpanV2bWs5cmp3djMzNzczM0AuLzNjMV8wXl4xLzFgX2ItYSMwZWhhMmQ0X2VgLS1kMTZzcw%3D%3D&btag=e00088000&expire=1738258498&l=2025012817342557A716FA7108B4677ED2&ply_type=2&policy=2&signature=63b211c124ca63d46a097133936f8c6e&tk=tt_chain_token",
                                "https://www.tiktok.com/aweme/v1/play/?faid=1988&file_id=04ecb0c1432545aea234b449f2682b1d&is_play_url=1&item_id=7432020938117369094&line=0&ply_type=2&signaturev3=dmlkZW9faWQ7ZmlsZV9pZDtpdGVtX2lkLjVmMjY0ZmZmNzBiYjgyN2ZjNzcwYmNhNWRlY2FmY2Yy&tk=tt_chain_token&video_id=v09044g40000cshtbg7og65hdjkshr3g"
                            ],
                            "Width": 576
                        },
                        "QualityType": 28
                    }
                ],
                "claInfo": {
                    "enableAutoCaption": true,
                    "hasOriginalAudio": true,
                    "noCaptionReason": 3
                },
                "codecType": "h264",
                "cover": "https://p16-sign-va.tiktokcdn.com/obj/tos-maliva-p-0068/o4EnjvAEUPbIA1VhiQBiMiGllGBZWyA7BAWA1?lk3s=b59d6b55&x-expires=1738256400&x-signature=MAUpOHMDkKAroN7P%2Fy%2BPaqI5PUc%3D&shp=b59d6b55&shcp=-",
                "definition": "540p",
                "downloadAddr": "https://v16-webapp-prime.tiktok.com/video/tos/useast2a/tos-useast2a-pve-0068/ocjDHwAIiQVkPOxyBUpvZ71iIQ8B77bnPSEAE/?a=1988&bti=NDU3ZjAwOg%3D%3D&ch=0&cr=3&dr=0&lr=all&cd=0%7C0%7C0%7C&cv=1&br=1552&bt=776&cs=0&ds=3&ft=4fUEKMRh8Zmo0TM83b4jVcUerpWrKsd.&mime_type=video_mp4&qs=0&rc=Mzk7aDk7ZGhlaGQ4NzM5NEBpanV2bWs5cmp3djMzNzczM0AyXzUwNS9eNjExLjU2LS4tYSMwZWhhMmQ0X2VgLS1kMTZzcw%3D%3D&btag=e00088000&expire=1738258498&l=2025012817342557A716FA7108B4677ED2&ply_type=2&policy=2&signature=302151045ed92d1a6bbfbf4390a39505&tk=tt_chain_token",
                "duration": 31,
                "dynamicCover": "https://p16-sign-va.tiktokcdn.com/obj/tos-maliva-p-0068/o4EnjvAEUPbIA1VhiQBiMiGllGBZWyA7BAWA1?lk3s=b59d6b55&x-expires=1738256400&x-signature=MAUpOHMDkKAroN7P%2Fy%2BPaqI5PUc%3D&shp=b59d6b55&shcp=-",
                "encodeUserTag": "",
                "encodedType": "normal",
                "format": "mp4",
                "height": 1024,
                "id": "7432020938117369094",
                "originCover": "https://p16-sign-va.tiktokcdn.com/obj/tos-maliva-p-0068/oIIZjy16iPUiPFBIAxnHQEBQVU7bAwtOx7ITS?lk3s=b59d6b55&x-expires=1738256400&x-signature=gm11a%2BjGmUzZU6kviUdVmcOVFn4%3D&shp=b59d6b55&shcp=-",
                "playAddr": "https://v16-webapp-prime.tiktok.com/video/tos/alisg/tos-alisg-pve-0037c001/ogkByBAQHniBDExOEcQWwqj7ZjIPIUV7P1iSb/?a=1988&bti=NDU3ZjAwOg%3D%3D&ch=0&cr=3&dr=0&lr=all&cd=0%7C0%7C0%7C&cv=1&br=858&bt=429&cs=0&ds=6&ft=4fUEKMRh8Zmo0TM83b4jVcUerpWrKsd.&mime_type=video_mp4&qs=4&rc=aWRlZ2U5OWZoOzM8aDo8OkBpanV2bWs5cmp3djMzNzczM0BiNjU2XmE1X2IxNWJiYS4yYSMwZWhhMmQ0X2VgLS1kMTZzcw%3D%3D&btag=e00088000&expire=1738258498&l=2025012817342557A716FA7108B4677ED2&ply_type=2&policy=2&signature=f652a8a0139232fd9bb91b10bc364add&tk=tt_chain_token",
                "ratio": "540p",
                "reflowCover": "https://p16-sign-va.tiktokcdn.com/tos-maliva-p-0068/o4EnjvAEUPbIA1VhiQBiMiGllGBZWyA7BAWA1~tplv-photomode-video-cover:480:480.jpeg?lk3s=b59d6b55&x-expires=1738256400&x-signature=IwWIUiy8xhcfTom%2BCV3UTvhPcL4%3D&shp=b59d6b55&shcp=-",
                "shareCover": [
                    "",
                    "https://p16-sign-va.tiktokcdn.com/tos-maliva-p-0068/oIIZjy16iPUiPFBIAxnHQEBQVU7bAwtOx7ITS~tplv-photomode-tiktok-play.jpeg?lk3s=b59d6b55&x-expires=1738688400&x-signature=XMzHeBubjK8FrduqAIqp%2BFuFYss%3D&shp=b59d6b55&shcp=-",
                    "https://p16-sign-va.tiktokcdn.com/tos-maliva-p-0068/oIIZjy16iPUiPFBIAxnHQEBQVU7bAwtOx7ITS~tplv-photomode-share-play.jpeg?lk3s=b59d6b55&x-expires=1738688400&x-signature=iqm8oyV6%2Fbp8%2BUjX9jYHs2S1Wzc%3D&shp=b59d6b55&shcp=-"
                ],
                "size": 1745976,
                "videoQuality": "lower",
                "volumeInfo": {
                    "Loudness": -13,
                    "Peak": 0.98855
                },
                "width": 576,
                "zoomCover": {
                    "240": "https://p16-sign-va.tiktokcdn.com/tos-maliva-p-0068/o4EnjvAEUPbIA1VhiQBiMiGllGBZWyA7BAWA1~tplv-photomode-zoomcover:240:240.avif?lk3s=b59d6b55&x-expires=1738256400&x-signature=0edA09PDBygBQUxiRTuOO7trxzE%3D&shp=b59d6b55&shcp=-",
                    "480": "https://p16-sign-va.tiktokcdn.com/tos-maliva-p-0068/o4EnjvAEUPbIA1VhiQBiMiGllGBZWyA7BAWA1~tplv-photomode-zoomcover:480:480.avif?lk3s=b59d6b55&x-expires=1738256400&x-signature=wYF57UB1bHCwp18cgO7p6%2B1PtM4%3D&shp=b59d6b55&shcp=-",
                    "720": "https://p16-sign-va.tiktokcdn.com/tos-maliva-p-0068/o4EnjvAEUPbIA1VhiQBiMiGllGBZWyA7BAWA1~tplv-photomode-zoomcover:720:720.avif?lk3s=b59d6b55&x-expires=1738256400&x-signature=iWCTN1Pec8Fe9IaLPSpKVCrPBaI%3D&shp=b59d6b55&shcp=-",
                    "960": "https://p16-sign-va.tiktokcdn.com/tos-maliva-p-0068/o4EnjvAEUPbIA1VhiQBiMiGllGBZWyA7BAWA1~tplv-photomode-zoomcover:960:960.avif?lk3s=b59d6b55&x-expires=1738256400&x-signature=B78wWgWnsuz6wHtcZuKofbpt1Yk%3D&shp=b59d6b55&shcp=-"
                }
            },
            "vl1": false
        },
        {
            "AIGCDescription": "",
            "BAInfo": "",
            "CategoryType": 120,
            "adAuthorization": false,
            "adLabelVersion": 0,
            "aigcLabelType": 0,
            "anchors": [
                {
                    "description": "CapCut \u00ac\u2211 Video Editor",
                    "extraInfo": {
                        "subtype": ""
                    },
                    "icon": {
                        "urlList": [
                            "https://p77-sg.tiktokcdn.com/obj/tiktok-obj/capcut_logo_64px_bk.png?shp=b59d6b55&shcp=-"
                        ]
                    },
                    "id": "0",
                    "keyword": "CapCut \u00ac\u2211 Try this template",
                    "logExtra": "{\"anchor_id\":0,\"anchor_name\":\"CapCut \u00ac\u2211 Try this template\",\"anchor_name_type\":\"template_0\",\"anchor_title_detail\":\"None\",\"anchor_type\":\"TT_CAPCUT\",\"capability_key\":\"none\",\"cc_template_pay_type\":0,\"if_device_language\":\"none\",\"if_race_trigger\":0,\"is_two_line\":0,\"maker_source\":\"\",\"template_id\":\"7434949337592892688\",\"tutorial_id\":\"none\",\"viamaker_anchor_capability_key_weight\":1,\"viamaker_anchor_style_idx\":-1,\"viamaker_anchor_style_source\":3,\"video_source\":0,\"video_type_id\":2}",
                    "schema": "https://www.capcut.com/editor-template?scenario=tiktok&utm_campaign=71351105&utm_content=7434949337592892688&utm_medium=tiktok_anchor&utm_source=tiktok_anchor_template",
                    "thumbnail": {
                        "height": 64,
                        "urlList": [
                            "https://p77-sg.tiktokcdn.com/obj/tiktok-obj/64x_Capcut3x.png?shp=b59d6b55&shcp=-"
                        ],
                        "width": 64
                    },
                    "type": 54
                }
            ],
            "author": {
                "avatarLarger": "https://p16-sign-sg.tiktokcdn.com/aweme/1080x1080/tos-alisg-avt-0068/0f1ad8f2fe1b346f7be9fe46361e6df9.jpeg?lk3s=a5d48078&nonce=1741&refresh_token=3e24f8b866f0895e68ef9fa1979fdb80&x-expires=1738256400&x-signature=JaG8Qv4yNiyfUf1%2BSXfFRWWSecQ%3D&shp=a5d48078&shcp=b59d6b55",
                "avatarMedium": "https://p16-sign-sg.tiktokcdn.com/aweme/720x720/tos-alisg-avt-0068/0f1ad8f2fe1b346f7be9fe46361e6df9.jpeg?lk3s=a5d48078&nonce=20974&refresh_token=f2935e0fa67487fd11341b534cf75eb7&x-expires=1738256400&x-signature=UsoS5ugBBlSdShr9F0A2NicZq0Q%3D&shp=a5d48078&shcp=b59d6b55",
                "avatarThumb": "https://p16-sign-sg.tiktokcdn.com/aweme/100x100/tos-alisg-avt-0068/0f1ad8f2fe1b346f7be9fe46361e6df9.jpeg?lk3s=a5d48078&nonce=9295&refresh_token=758aa8e24b0324833b315d000a5c1bfd&x-expires=1738256400&x-signature=zvUhtcXERSVThmQNEjpXG5Ow6lo%3D&shp=a5d48078&shcp=b59d6b55",
                "commentSetting": 0,
                "downloadSetting": 0,
                "duetSetting": 0,
                "ftc": false,
                "id": "7346303413288305671",
                "isADVirtual": false,
                "isEmbedBanned": false,
                "nickname": "Musicazina",
                "openFavorite": true,
                "privateAccount": false,
                "relation": 0,
                "secUid": "MS4wLjABAAAAOcFLu8YWFcxvtGA8gu5ETV4yjYgSQebeacq1URG2e0ZMw97SB50bteltslP8v5Vn",
                "secret": false,
                "signature": "",
                "stitchSetting": 0,
                "ttSeller": false,
                "uniqueId": "p1_t26",
                "verified": false
            },
            "authorStats": {
                "diggCount": 75500,
                "followerCount": 202100,
                "followingCount": 27,
                "friendCount": 0,
                "heart": 3500000,
                "heartCount": 3500000,
                "videoCount": 111
            },
            "backendSourceEventTracking": "fyp_32",
            "challenges": [
                {
                    "coverLarger": "",
                    "coverMedium": "",
                    "coverThumb": "",
                    "desc": "",
                    "id": "1690429300153350",
                    "isCommerce": false,
                    "profileLarger": "",
                    "profileMedium": "",
                    "profileThumb": "",
                    "stats": {
                        "videoCount": 0,
                        "viewCount": 0
                    },
                    "title": "\u0178\u00d6\u00ff\u2260\u00ff\u220f\u0178\u00e0\u00ff\u00b1_\u0178\u00d6\u0178\u00dc_\u00ff\u00df\u0178\u00d1\u00ff\u00df\u0178\u00c9\u00ff\u2265\u00ff\u00ae\u0178\u00d1\u0178\u00e0\u00ff\u00b1\uf8ff\u00fc\u2022\u222b"
                },
                {
                    "coverLarger": "",
                    "coverMedium": "",
                    "coverThumb": "",
                    "desc": "",
                    "id": "42164",
                    "isCommerce": false,
                    "profileLarger": "",
                    "profileMedium": "",
                    "profileThumb": "",
                    "stats": {
                        "videoCount": 0,
                        "viewCount": 0
                    },
                    "title": "foryou"
                },
                {
                    "coverLarger": "",
                    "coverMedium": "",
                    "coverThumb": "",
                    "desc": "",
                    "id": "1612306392542213",
                    "isCommerce": false,
                    "profileLarger": "",
                    "profileMedium": "",
                    "profileThumb": "",
                    "stats": {
                        "videoCount": 0,
                        "viewCount": 0
                    },
                    "title": "\u00ff\u00a5\u00ff\u00df\u00ff\u00a5\u0178\u00e1_\u00ff\u2265\u0178\u00e0\u00ff\u00d8\u00ff\u00df\u00ff\u00b0"
                },
                {
                    "coverLarger": "",
                    "coverMedium": "",
                    "coverThumb": "",
                    "desc": "",
                    "id": "7225464033724334081",
                    "isCommerce": false,
                    "profileLarger": "",
                    "profileMedium": "",
                    "profileThumb": "",
                    "stats": {
                        "videoCount": 0,
                        "viewCount": 0
                    },
                    "title": "bilal_hamoud"
                },
                {
                    "coverLarger": "",
                    "coverMedium": "",
                    "coverThumb": "",
                    "desc": "",
                    "id": "1675485588080645",
                    "isCommerce": false,
                    "profileLarger": "",
                    "profileMedium": "",
                    "profileThumb": "",
                    "stats": {
                        "videoCount": 0,
                        "viewCount": 0
                    },
                    "title": "\u00ff\u00df\u0178\u00d1\u00ff\u00a5\u00ff\u03c0\u00ff\u00ae_\u00ff\u00df\u0178\u00d1\u00ff\u00b5\u0178\u00e4\u0178\u00dc\u0178\u00e4_\u0178\u00d6\u00ff\u00df\u0178\u00d1\u0178\u00e1_\u00ff\u2260\u0178\u00d1\uf8ff\u00fc\u00f2\u00c7\uf8ff\u00fc\u00f2\u00c7"
                },
                {
                    "coverLarger": "",
                    "coverMedium": "",
                    "coverThumb": "",
                    "desc": "",
                    "id": "7046760603024621570",
                    "isCommerce": false,
                    "profileLarger": "",
                    "profileMedium": "",
                    "profileThumb": "",
                    "stats": {
                        "videoCount": 0,
                        "viewCount": 0
                    },
                    "title": "\u00ff\u2122\u00ff\u00b1\u0178\u00dc\u00ff\u00d8_\u00ff\u00a5\u00ff\u00df\u00ff\u00a5\u00ff\u00a9_\u00ff\u2265\u0178\u00e0\u00ff\u00d8\u00ff\u00df\u00ff\u00b0_\uf8ff\u00fc\u00f4\u00e3\u201a\u00f9\u00a7"
                },
                {
                    "coverLarger": "",
                    "coverMedium": "",
                    "coverThumb": "",
                    "desc": "",
                    "id": "7082571149460111361",
                    "isCommerce": false,
                    "profileLarger": "",
                    "profileMedium": "",
                    "profileThumb": "",
                    "stats": {
                        "videoCount": 0,
                        "viewCount": 0
                    },
                    "title": "\u0178\u00c7\u00ff\u00df\u0178\u00d1\u00ff\u00ae_\u0178\u00c9\u00ff\u00df\u00ff\u00ae_\u0178\u00c9\u00ff\u00df\u00ff\u2122"
                },
                {
                    "coverLarger": "",
                    "coverMedium": "",
                    "coverThumb": "",
                    "desc": "",
                    "id": "1636506984048646",
                    "isCommerce": false,
                    "profileLarger": "",
                    "profileMedium": "",
                    "profileThumb": "",
                    "stats": {
                        "videoCount": 0,
                        "viewCount": 0
                    },
                    "title": "\u00ff\u2122\u00ff\u00b5\u0178\u00d6\u0178\u00e4\u0178\u00d6_\u0178\u00c5\u0178\u00e4\u00ff\u00d8\u0178\u00e4\u0178\u00e0\u0178\u00e1\u00ff\u00df\u00ff\u2122\uf8ff\u00fc\u00e9\u2202\uf8ff\u00fc\u00e9\u00a7\uf8ff\u00fc\u00e9\u00a8"
                },
                {
                    "coverLarger": "",
                    "coverMedium": "",
                    "coverThumb": "",
                    "desc": "",
                    "id": "229207",
                    "isCommerce": false,
                    "profileLarger": "",
                    "profileMedium": "",
                    "profileThumb": "",
                    "stats": {
                        "videoCount": 0,
                        "viewCount": 0
                    },
                    "title": "fyp"
                },
                {
                    "coverLarger": "",
                    "coverMedium": "",
                    "coverThumb": "",
                    "desc": "",
                    "id": "7351847627502059526",
                    "isCommerce": false,
                    "profileLarger": "",
                    "profileMedium": "",
                    "profileThumb": "",
                    "stats": {
                        "videoCount": 0,
                        "viewCount": 0
                    },
                    "title": "\u0178\u00c7\u0178\u00e0\u00ff\u00df\u0178\u00d1\u00ff\u00ae_\u00ff\u00a8\u0178\u00dc\u0178\u00e4\u00ff\u00b1\u00ff\u00df\u0178\u00d1"
                }
            ],
            "collected": false,
            "contents": [
                {
                    "desc": "\u00ff\u00df\u0178\u00dc\u00ff\u00df \u00ff\u00ae\u00ff\u00b1\u0178\u00e0\u00ff\u2260\u0178\u00e4 \u0178\u00c9\u00ff\u00ae\u00ff\u00b1 \u201a\u00fa\u00ae\uf8ff\u00fc\u00a7\u00e7 \u00ff\u2260\u00ff\u2211 \u00ff\u00b5\u0178\u00e0\u00ff\u00b1\u00ff\u2122\u0178\u00c9 \uf8ff\u00fc\u00ee\u2022\u201a\u00fa\u00ae #\u0178\u00d6\u00ff\u2260\u00ff\u220f\u0178\u00e0\u00ff\u00b1_\u0178\u00d6\u0178\u00dc_\u00ff\u00df\u0178\u00d1\u00ff\u00df\u0178\u00c9\u00ff\u2265\u00ff\u00ae\u0178\u00d1\u0178\u00e0\u00ff\u00b1\uf8ff\u00fc\u2022\u222b #foryou #\u00ff\u00a5\u00ff\u00df\u00ff\u00a5\u0178\u00e1_\u00ff\u2265\u0178\u00e0\u00ff\u00d8\u00ff\u00df\u00ff\u00b0 #bilal_hamoud #\u00ff\u00df\u0178\u00d1\u00ff\u00a5\u00ff\u03c0\u00ff\u00ae_\u00ff\u00df\u0178\u00d1\u00ff\u00b5\u0178\u00e4\u0178\u00dc\u0178\u00e4_\u0178\u00d6\u00ff\u00df\u0178\u00d1\u0178\u00e1_\u00ff\u2260\u0178\u00d1\uf8ff\u00fc\u00f2\u00c7\uf8ff\u00fc\u00f2\u00c7 #\u00ff\u2122\u00ff\u00b1\u0178\u00dc\u00ff\u00d8_\u00ff\u00a5\u00ff\u00df\u00ff\u00a5\u00ff\u00a9_\u00ff\u2265\u0178\u00e0\u00ff\u00d8\u00ff\u00df\u00ff\u00b0_\uf8ff\u00fc\u00f4\u00e3\u201a\u00f9\u00a7 #\u0178\u00c7\u00ff\u00df\u0178\u00d1\u00ff\u00ae_\u0178\u00c9\u00ff\u00df\u00ff\u00ae_\u0178\u00c9\u00ff\u00df\u00ff\u2122 #\u00ff\u2122\u00ff\u00b5\u0178\u00d6\u0178\u00e4\u0178\u00d6_\u0178\u00c5\u0178\u00e4\u00ff\u00d8\u0178\u00e4\u0178\u00e0\u0178\u00e1\u00ff\u00df\u00ff\u2122\uf8ff\u00fc\u00e9\u2202\uf8ff\u00fc\u00e9\u00a7\uf8ff\u00fc\u00e9\u00a8 #fyp #\u0178\u00c7\u0178\u00e0\u00ff\u00df\u0178\u00d1\u00ff\u00ae_\u00ff\u00a8\u0178\u00dc\u0178\u00e4\u00ff\u00b1\u00ff\u00df\u0178\u00d1 ",
                    "textExtra": [
                        {
                            "awemeId": "",
                            "end": 52,
                            "hashtagId": "1690429300153350",
                            "hashtagName": "\u0178\u00d6\u00ff\u2260\u00ff\u220f\u0178\u00e0\u00ff\u00b1_\u0178\u00d6\u0178\u00dc_\u00ff\u00df\u0178\u00d1\u00ff\u00df\u0178\u00c9\u00ff\u2265\u00ff\u00ae\u0178\u00d1\u0178\u00e0\u00ff\u00b1\uf8ff\u00fc\u2022\u222b",
                            "isCommerce": false,
                            "secUid": "",
                            "start": 31,
                            "subType": 0,
                            "type": 1,
                            "userId": "",
                            "userUniqueId": ""
                        },
                        {
                            "awemeId": "",
                            "end": 60,
                            "hashtagId": "42164",
                            "hashtagName": "foryou",
                            "isCommerce": false,
                            "secUid": "",
                            "start": 53,
                            "subType": 0,
                            "type": 1,
                            "userId": "",
                            "userUniqueId": ""
                        },
                        {
                            "awemeId": "",
                            "end": 72,
                            "hashtagId": "1612306392542213",
                            "hashtagName": "\u00ff\u00a5\u00ff\u00df\u00ff\u00a5\u0178\u00e1_\u00ff\u2265\u0178\u00e0\u00ff\u00d8\u00ff\u00df\u00ff\u00b0",
                            "isCommerce": false,
                            "secUid": "",
                            "start": 61,
                            "subType": 0,
                            "type": 1,
                            "userId": "",
                            "userUniqueId": ""
                        },
                        {
                            "awemeId": "",
                            "end": 86,
                            "hashtagId": "7225464033724334081",
                            "hashtagName": "bilal_hamoud",
                            "isCommerce": false,
                            "secUid": "",
                            "start": 73,
                            "subType": 0,
                            "type": 1,
                            "userId": "",
                            "userUniqueId": ""
                        },
                        {
                            "awemeId": "",
                            "end": 112,
                            "hashtagId": "1675485588080645",
                            "hashtagName": "\u00ff\u00df\u0178\u00d1\u00ff\u00a5\u00ff\u03c0\u00ff\u00ae_\u00ff\u00df\u0178\u00d1\u00ff\u00b5\u0178\u00e4\u0178\u00dc\u0178\u00e4_\u0178\u00d6\u00ff\u00df\u0178\u00d1\u0178\u00e1_\u00ff\u2260\u0178\u00d1\uf8ff\u00fc\u00f2\u00c7\uf8ff\u00fc\u00f2\u00c7",
                            "isCommerce": false,
                            "secUid": "",
                            "start": 87,
                            "subType": 0,
                            "type": 1,
                            "userId": "",
                            "userUniqueId": ""
                        },
                        {
                            "awemeId": "",
                            "end": 133,
                            "hashtagId": "7046760603024621570",
                            "hashtagName": "\u00ff\u2122\u00ff\u00b1\u0178\u00dc\u00ff\u00d8_\u00ff\u00a5\u00ff\u00df\u00ff\u00a5\u00ff\u00a9_\u00ff\u2265\u0178\u00e0\u00ff\u00d8\u00ff\u00df\u00ff\u00b0_\uf8ff\u00fc\u00f4\u00e3\u201a\u00f9\u00a7",
                            "isCommerce": false,
                            "secUid": "",
                            "start": 113,
                            "subType": 0,
                            "type": 1,
                            "userId": "",
                            "userUniqueId": ""
                        },
                        {
                            "awemeId": "",
                            "end": 147,
                            "hashtagId": "7082571149460111361",
                            "hashtagName": "\u0178\u00c7\u00ff\u00df\u0178\u00d1\u00ff\u00ae_\u0178\u00c9\u00ff\u00df\u00ff\u00ae_\u0178\u00c9\u00ff\u00df\u00ff\u2122",
                            "isCommerce": false,
                            "secUid": "",
                            "start": 134,
                            "subType": 0,
                            "type": 1,
                            "userId": "",
                            "userUniqueId": ""
                        },
                        {
                            "awemeId": "",
                            "end": 169,
                            "hashtagId": "1636506984048646",
                            "hashtagName": "\u00ff\u2122\u00ff\u00b5\u0178\u00d6\u0178\u00e4\u0178\u00d6_\u0178\u00c5\u0178\u00e4\u00ff\u00d8\u0178\u00e4\u0178\u00e0\u0178\u00e1\u00ff\u00df\u00ff\u2122\uf8ff\u00fc\u00e9\u2202\uf8ff\u00fc\u00e9\u00a7\uf8ff\u00fc\u00e9\u00a8",
                            "isCommerce": false,
                            "secUid": "",
                            "start": 148,
                            "subType": 0,
                            "type": 1,
                            "userId": "",
                            "userUniqueId": ""
                        },
                        {
                            "awemeId": "",
                            "end": 174,
                            "hashtagId": "229207",
                            "hashtagName": "fyp",
                            "isCommerce": false,
                            "secUid": "",
                            "start": 170,
                            "subType": 0,
                            "type": 1,
                            "userId": "",
                            "userUniqueId": ""
                        },
                        {
                            "awemeId": "",
                            "end": 188,
                            "hashtagId": "7351847627502059526",
                            "hashtagName": "\u0178\u00c7\u0178\u00e0\u00ff\u00df\u0178\u00d1\u00ff\u00ae_\u00ff\u00a8\u0178\u00dc\u0178\u00e4\u00ff\u00b1\u00ff\u00df\u0178\u00d1",
                            "isCommerce": false,
                            "secUid": "",
                            "start": 175,
                            "subType": 0,
                            "type": 1,
                            "userId": "",
                            "userUniqueId": ""
                        }
                    ]
                }
            ],
            "createTime": 1731509144,
            "desc": "\u00ff\u00df\u0178\u00dc\u00ff\u00df \u00ff\u00ae\u00ff\u00b1\u0178\u00e0\u00ff\u2260\u0178\u00e4 \u0178\u00c9\u00ff\u00ae\u00ff\u00b1 \u201a\u00fa\u00ae\uf8ff\u00fc\u00a7\u00e7 \u00ff\u2260\u00ff\u2211 \u00ff\u00b5\u0178\u00e0\u00ff\u00b1\u00ff\u2122\u0178\u00c9 \uf8ff\u00fc\u00ee\u2022\u201a\u00fa\u00ae #\u0178\u00d6\u00ff\u2260\u00ff\u220f\u0178\u00e0\u00ff\u00b1_\u0178\u00d6\u0178\u00dc_\u00ff\u00df\u0178\u00d1\u00ff\u00df\u0178\u00c9\u00ff\u2265\u00ff\u00ae\u0178\u00d1\u0178\u00e0\u00ff\u00b1\uf8ff\u00fc\u2022\u222b #foryou #\u00ff\u00a5\u00ff\u00df\u00ff\u00a5\u0178\u00e1_\u00ff\u2265\u0178\u00e0\u00ff\u00d8\u00ff\u00df\u00ff\u00b0 #bilal_hamoud #\u00ff\u00df\u0178\u00d1\u00ff\u00a5\u00ff\u03c0\u00ff\u00ae_\u00ff\u00df\u0178\u00d1\u00ff\u00b5\u0178\u00e4\u0178\u00dc\u0178\u00e4_\u0178\u00d6\u00ff\u00df\u0178\u00d1\u0178\u00e1_\u00ff\u2260\u0178\u00d1\uf8ff\u00fc\u00f2\u00c7\uf8ff\u00fc\u00f2\u00c7 #\u00ff\u2122\u00ff\u00b1\u0178\u00dc\u00ff\u00d8_\u00ff\u00a5\u00ff\u00df\u00ff\u00a5\u00ff\u00a9_\u00ff\u2265\u0178\u00e0\u00ff\u00d8\u00ff\u00df\u00ff\u00b0_\uf8ff\u00fc\u00f4\u00e3\u201a\u00f9\u00a7 #\u0178\u00c7\u00ff\u00df\u0178\u00d1\u00ff\u00ae_\u0178\u00c9\u00ff\u00df\u00ff\u00ae_\u0178\u00c9\u00ff\u00df\u00ff\u2122 #\u00ff\u2122\u00ff\u00b5\u0178\u00d6\u0178\u00e4\u0178\u00d6_\u0178\u00c5\u0178\u00e4\u00ff\u00d8\u0178\u00e4\u0178\u00e0\u0178\u00e1\u00ff\u00df\u00ff\u2122\uf8ff\u00fc\u00e9\u2202\uf8ff\u00fc\u00e9\u00a7\uf8ff\u00fc\u00e9\u00a8 #fyp #\u0178\u00c7\u0178\u00e0\u00ff\u00df\u0178\u00d1\u00ff\u00ae_\u00ff\u00a8\u0178\u00dc\u0178\u00e4\u00ff\u00b1\u00ff\u00df\u0178\u00d1 ",
            "digged": false,
            "diversificationId": 10046,
            "duetDisplay": 0,
            "duetEnabled": true,
            "duetInfo": {
                "duetFromId": "0"
            },
            "forFriend": false,
            "id": "7436775132342848786",
            "isAd": false,
            "itemCommentStatus": 0,
            "itemMute": false,
            "item_control": {
                "can_repost": true
            },
            "music": {
                "album": "",
                "authorName": "\u00ff\u00ae\u0178\u00c4\u0178\u00c4\u0178\u00c4\u00ff\u00df\u00ff\u00b1\u0178\u00e4 || \uf8ff\u00f9\u00ea\u00c5\uf8ff\u00f9\u00ea\u00c4\uf8ff\u00f9\u00ea\u00eb\uf8ff\u00f9\u00ea\u00eb\uf8ff\u00f9\u00ea\u00f2",
                "coverLarge": "https://p16-sign-sg.tiktokcdn.com/aweme/1080x1080/tos-alisg-avt-0068/2a599f635f4c0b19f07dbddd8d79f4e5.jpeg?lk3s=a5d48078&nonce=88541&refresh_token=06a6c19add2f7355503c751866bc7bbe&x-expires=1738256400&x-signature=9mJQdVTJ3GI%2FYwkyPboG%2B4cnixE%3D&shp=a5d48078&shcp=b59d6b55",
                "coverMedium": "https://p77-sign-sg.tiktokcdn.com/aweme/720x720/tos-alisg-avt-0068/2a599f635f4c0b19f07dbddd8d79f4e5.jpeg?lk3s=a5d48078&nonce=80198&refresh_token=0f67b438896db6c03fb3418feabb6f51&x-expires=1738256400&x-signature=aNya2j%2B54F71To7WpUrGwTpn5VM%3D&shp=a5d48078&shcp=b59d6b55",
                "coverThumb": "https://p77-sign-sg.tiktokcdn.com/aweme/100x100/tos-alisg-avt-0068/2a599f635f4c0b19f07dbddd8d79f4e5.jpeg?lk3s=a5d48078&nonce=59950&refresh_token=615216c8a9756c0f0c78ced1b5ae92b3&x-expires=1738256400&x-signature=IAY%2Fa7W3BNkzZ2w%2BjRQ9PNK0mdY%3D&shp=a5d48078&shcp=b59d6b55",
                "duration": 24,
                "id": "7434952596391414529",
                "isCopyrighted": false,
                "original": true,
                "playUrl": "https://v77.tiktokcdn-eu.com/f01d762dd7b26ff0ccbc779433d6ec0e/679a66bb/video/tos/alisg/tos-alisg-v-27dcd7/ogyzL8NfMM55WXKhfcQhgrQAcKAYVieAiaMffS/?a=1233&bti=NDU3ZjAwOg%3D%3D&ch=0&cr=0&dr=0&er=2&cd=0%7C0%7C0%7C0&br=250&bt=125&ft=.NpOcInz7ThF3nLOXq8Zmo&mime_type=audio_mpeg&qs=6&rc=O2g2Ozw4OzllZGk2ZzlnZ0BpajlkZW45cnk3djMzODU8NEAvNGAwLzYzXzYxYmEuXjBiYSNscnI2MmRzMGtgLS1kMS1zcw%3D%3D&vvpl=1&l=2025012817342557A716FA7108B4677ED2&btag=e000b8000&download=true",
                "title": "\u00ff\u00df\u0178\u00d1\u00ff\u00b5\u0178\u00e0\u00ff\u2122 \u00ff\u00df\u0178\u00d1\u00ff\u00a3\u00ff\u00b5\u0178\u00d1\u0178\u00e4"
            },
            "officalItem": false,
            "originalItem": false,
            "playlistId": "",
            "privateItem": false,
            "secret": false,
            "shareEnabled": true,
            "showNotPass": false,
            "stats": {
                "collectCount": 15600,
                "commentCount": 143,
                "diggCount": 100500,
                "playCount": 2200000,
                "shareCount": 2520
            },
            "statsV2": {
                "collectCount": "15605",
                "commentCount": "143",
                "diggCount": "100519",
                "playCount": "2244404",
                "repostCount": "0",
                "shareCount": "2520"
            },
            "stitchDisplay": 0,
            "stitchEnabled": true,
            "textExtra": [
                {
                    "awemeId": "",
                    "end": 52,
                    "hashtagId": "1690429300153350",
                    "hashtagName": "\u0178\u00d6\u00ff\u2260\u00ff\u220f\u0178\u00e0\u00ff\u00b1_\u0178\u00d6\u0178\u00dc_\u00ff\u00df\u0178\u00d1\u00ff\u00df\u0178\u00c9\u00ff\u2265\u00ff\u00ae\u0178\u00d1\u0178\u00e0\u00ff\u00b1\uf8ff\u00fc\u2022\u222b",
                    "isCommerce": false,
                    "secUid": "",
                    "start": 31,
                    "subType": 0,
                    "type": 1,
                    "userId": "",
                    "userUniqueId": ""
                },
                {
                    "awemeId": "",
                    "end": 60,
                    "hashtagId": "42164",
                    "hashtagName": "foryou",
                    "isCommerce": false,
                    "secUid": "",
                    "start": 53,
                    "subType": 0,
                    "type": 1,
                    "userId": "",
                    "userUniqueId": ""
                },
                {
                    "awemeId": "",
                    "end": 72,
                    "hashtagId": "1612306392542213",
                    "hashtagName": "\u00ff\u00a5\u00ff\u00df\u00ff\u00a5\u0178\u00e1_\u00ff\u2265\u0178\u00e0\u00ff\u00d8\u00ff\u00df\u00ff\u00b0",
                    "isCommerce": false,
                    "secUid": "",
                    "start": 61,
                    "subType": 0,
                    "type": 1,
                    "userId": "",
                    "userUniqueId": ""
                },
                {
                    "awemeId": "",
                    "end": 86,
                    "hashtagId": "7225464033724334081",
                    "hashtagName": "bilal_hamoud",
                    "isCommerce": false,
                    "secUid": "",
                    "start": 73,
                    "subType": 0,
                    "type": 1,
                    "userId": "",
                    "userUniqueId": ""
                },
                {
                    "awemeId": "",
                    "end": 112,
                    "hashtagId": "1675485588080645",
                    "hashtagName": "\u00ff\u00df\u0178\u00d1\u00ff\u00a5\u00ff\u03c0\u00ff\u00ae_\u00ff\u00df\u0178\u00d1\u00ff\u00b5\u0178\u00e4\u0178\u00dc\u0178\u00e4_\u0178\u00d6\u00ff\u00df\u0178\u00d1\u0178\u00e1_\u00ff\u2260\u0178\u00d1\uf8ff\u00fc\u00f2\u00c7\uf8ff\u00fc\u00f2\u00c7",
                    "isCommerce": false,
                    "secUid": "",
                    "start": 87,
                    "subType": 0,
                    "type": 1,
                    "userId": "",
                    "userUniqueId": ""
                },
                {
                    "awemeId": "",
                    "end": 133,
                    "hashtagId": "7046760603024621570",
                    "hashtagName": "\u00ff\u2122\u00ff\u00b1\u0178\u00dc\u00ff\u00d8_\u00ff\u00a5\u00ff\u00df\u00ff\u00a5\u00ff\u00a9_\u00ff\u2265\u0178\u00e0\u00ff\u00d8\u00ff\u00df\u00ff\u00b0_\uf8ff\u00fc\u00f4\u00e3\u201a\u00f9\u00a7",
                    "isCommerce": false,
                    "secUid": "",
                    "start": 113,
                    "subType": 0,
                    "type": 1,
                    "userId": "",
                    "userUniqueId": ""
                },
                {
                    "awemeId": "",
                    "end": 147,
                    "hashtagId": "7082571149460111361",
                    "hashtagName": "\u0178\u00c7\u00ff\u00df\u0178\u00d1\u00ff\u00ae_\u0178\u00c9\u00ff\u00df\u00ff\u00ae_\u0178\u00c9\u00ff\u00df\u00ff\u2122",
                    "isCommerce": false,
                    "secUid": "",
                    "start": 134,
                    "subType": 0,
                    "type": 1,
                    "userId": "",
                    "userUniqueId": ""
                },
                {
                    "awemeId": "",
                    "end": 169,
                    "hashtagId": "1636506984048646",
                    "hashtagName": "\u00ff\u2122\u00ff\u00b5\u0178\u00d6\u0178\u00e4\u0178\u00d6_\u0178\u00c5\u0178\u00e4\u00ff\u00d8\u0178\u00e4\u0178\u00e0\u0178\u00e1\u00ff\u00df\u00ff\u2122\uf8ff\u00fc\u00e9\u2202\uf8ff\u00fc\u00e9\u00a7\uf8ff\u00fc\u00e9\u00a8",
                    "isCommerce": false,
                    "secUid": "",
                    "start": 148,
                    "subType": 0,
                    "type": 1,
                    "userId": "",
                    "userUniqueId": ""
                },
                {
                    "awemeId": "",
                    "end": 174,
                    "hashtagId": "229207",
                    "hashtagName": "fyp",
                    "isCommerce": false,
                    "secUid": "",
                    "start": 170,
                    "subType": 0,
                    "type": 1,
                    "userId": "",
                    "userUniqueId": ""
                },
                {
                    "awemeId": "",
                    "end": 188,
                    "hashtagId": "7351847627502059526",
                    "hashtagName": "\u0178\u00c7\u0178\u00e0\u00ff\u00df\u0178\u00d1\u00ff\u00ae_\u00ff\u00a8\u0178\u00dc\u0178\u00e4\u00ff\u00b1\u00ff\u00df\u0178\u00d1",
                    "isCommerce": false,
                    "secUid": "",
                    "start": 175,
                    "subType": 0,
                    "type": 1,
                    "userId": "",
                    "userUniqueId": ""
                }
            ],
            "textLanguage": "ar",
            "textTranslatable": true,
            "video": {
                "VQScore": "66.1",
                "bitrate": 207419,
                "bitrateInfo": [
                    {
                        "Bitrate": 207419,
                        "CodecType": "h264",
                        "GearName": "lower_540_0",
                        "MVMAF": "\"\"",
                        "PlayAddr": {
                            "DataSize": 624930,
                            "FileCs": "c:0-16894-4647",
                            "FileHash": "fe55aafb7e44c96c5b00ede78862ab12",
                            "Height": 1024,
                            "Uri": "v14044g50000csqbmjfog65j635brr40",
                            "UrlKey": "v14044g50000csqbmjfog65j635brr40_h264_540p_207419",
                            "UrlList": [
                                "https://v16-webapp-prime.tiktok.com/video/tos/alisg/tos-alisg-pve-0037c001/oUN8EYCNgtmRAQVznEIRZfFRE7BpULfdB2TQDk/?a=1988&bti=NDU3ZjAwOg%3D%3D&ch=0&cr=3&dr=0&lr=all&cd=0%7C0%7C0%7C&cv=1&br=404&bt=202&cs=0&ds=6&ft=4fUEKMRh8Zmo0TM83b4jVcUerpWrKsd.&mime_type=video_mp4&qs=4&rc=Omg7NGg1ZzVnOTo2ODRmM0BpM3VlNm05cm1ldjMzODczNEAzMGI0NGNfXjAxNDQxY2NiYSMxbzIzMmRjam5gLS1kMTFzcw%3D%3D&btag=e000b8000&expire=1738258491&l=2025012817342557A716FA7108B4677ED2&ply_type=2&policy=2&signature=c59a6e357ae89abbef7eed35120f78a7&tk=tt_chain_token",
                                "https://v19-webapp-prime.tiktok.com/video/tos/alisg/tos-alisg-pve-0037c001/oUN8EYCNgtmRAQVznEIRZfFRE7BpULfdB2TQDk/?a=1988&bti=NDU3ZjAwOg%3D%3D&ch=0&cr=3&dr=0&lr=all&cd=0%7C0%7C0%7C&cv=1&br=404&bt=202&cs=0&ds=6&ft=4fUEKMRh8Zmo0TM83b4jVcUerpWrKsd.&mime_type=video_mp4&qs=4&rc=Omg7NGg1ZzVnOTo2ODRmM0BpM3VlNm05cm1ldjMzODczNEAzMGI0NGNfXjAxNDQxY2NiYSMxbzIzMmRjam5gLS1kMTFzcw%3D%3D&btag=e000b8000&expire=1738258491&l=2025012817342557A716FA7108B4677ED2&ply_type=2&policy=2&signature=c59a6e357ae89abbef7eed35120f78a7&tk=tt_chain_token",
                                "https://www.tiktok.com/aweme/v1/play/?faid=1988&file_id=e0fcf1457377463da2bdf27e71e83e67&is_play_url=1&item_id=7436775132342848786&line=0&ply_type=2&signaturev3=dmlkZW9faWQ7ZmlsZV9pZDtpdGVtX2lkLjlkNjQxZmNkMjgxNzI1NDNhZDU4YjM4MDRkMzE4NGFh&tk=tt_chain_token&video_id=v14044g50000csqbmjfog65j635brr40"
                            ],
                            "Width": 576
                        },
                        "QualityType": 24
                    },
                    {
                        "Bitrate": 200916,
                        "CodecType": "h265_hvc1",
                        "GearName": "adapt_lower_720_1",
                        "MVMAF": "\"{\\\"v2.0\\\": {\\\"ori\\\": {\\\"v1080\\\": 87.211, \\\"v960\\\": 88.561, \\\"v864\\\": 89.838, \\\"v720\\\": 92.112}, \\\"srv1\\\": {\\\"v1080\\\": 95.927, \\\"v960\\\": 96.747, \\\"v864\\\": 96.195, \\\"v720\\\": 98.452}}}\"",
                        "PlayAddr": {
                            "DataSize": 605337,
                            "FileCs": "c:0-17281-4d5c",
                            "FileHash": "7dd4ea464ee9c014d69ac1f5a5ebb75b",
                            "Height": 1280,
                            "Uri": "v14044g50000csqbmjfog65j635brr40",
                            "UrlKey": "v14044g50000csqbmjfog65j635brr40_bytevc1_720p_200916",
                            "UrlList": [
                                "https://v16-webapp-prime.tiktok.com/video/tos/alisg/tos-alisg-pve-0037c001/ocHlzAEz2JB9wqAmIMkCA2M1Iqi9Im7iLPzMfJ/?a=1988&bti=NDU3ZjAwOg%3D%3D&ch=0&cr=3&dr=0&lr=all&cd=0%7C0%7C0%7C&cv=1&br=392&bt=196&cs=2&ds=3&eid=12800&ft=4fUEKMRh8Zmo0TM83b4jVcUerpWrKsd.&mime_type=video_mp4&qs=14&rc=NTNkOzg6NGQ2NDRoOWdkPEBpM3VlNm05cm1ldjMzODczNEA1X2I0NS8wNmAxMS81YS4yYSMxbzIzMmRjam5gLS1kMTFzcw%3D%3D&btag=e000b8000&expire=1738258491&l=2025012817342557A716FA7108B4677ED2&ply_type=2&policy=2&signature=e4a0b2b1b3abf1bcd62c7cfc58c7d852&tk=tt_chain_token",
                                "https://v19-webapp-prime.tiktok.com/video/tos/alisg/tos-alisg-pve-0037c001/ocHlzAEz2JB9wqAmIMkCA2M1Iqi9Im7iLPzMfJ/?a=1988&bti=NDU3ZjAwOg%3D%3D&ch=0&cr=3&dr=0&lr=all&cd=0%7C0%7C0%7C&cv=1&br=392&bt=196&cs=2&ds=3&eid=12800&ft=4fUEKMRh8Zmo0TM83b4jVcUerpWrKsd.&mime_type=video_mp4&qs=14&rc=NTNkOzg6NGQ2NDRoOWdkPEBpM3VlNm05cm1ldjMzODczNEA1X2I0NS8wNmAxMS81YS4yYSMxbzIzMmRjam5gLS1kMTFzcw%3D%3D&btag=e000b8000&expire=1738258491&l=2025012817342557A716FA7108B4677ED2&ply_type=2&policy=2&signature=e4a0b2b1b3abf1bcd62c7cfc58c7d852&tk=tt_chain_token",
                                "https://www.tiktok.com/aweme/v1/play/?faid=1988&file_id=591add862e4141c39a31278578eab082&is_play_url=1&item_id=7436775132342848786&line=0&ply_type=2&signaturev3=dmlkZW9faWQ7ZmlsZV9pZDtpdGVtX2lkLmI3MzFlODc3NTYxYWNmYjVkMWI1Y2M3NGQwMGJiYzM0&tk=tt_chain_token&video_id=v14044g50000csqbmjfog65j635brr40"
                            ],
                            "Width": 720
                        },
                        "QualityType": 14
                    },
                    {
                        "Bitrate": 164724,
                        "CodecType": "h265_hvc1",
                        "GearName": "adapt_540_1",
                        "MVMAF": "\"{\\\"v2.0\\\": {\\\"ori\\\": {\\\"v1080\\\": 84.32, \\\"v960\\\": 85.65, \\\"v864\\\": 88.787, \\\"v720\\\": 91.152}, \\\"srv1\\\": {\\\"v1080\\\": 95.683, \\\"v960\\\": 96.66, \\\"v864\\\": 97.842, \\\"v720\\\": 97.793}}}\"",
                        "PlayAddr": {
                            "DataSize": 496295,
                            "FileCs": "c:0-17281-7c68",
                            "FileHash": "24893fd0ed2aa459e3c30acae7260009",
                            "Height": 1024,
                            "Uri": "v14044g50000csqbmjfog65j635brr40",
                            "UrlKey": "v14044g50000csqbmjfog65j635brr40_bytevc1_540p_164724",
                            "UrlList": [
                                "https://v16-webapp-prime.tiktok.com/video/tos/alisg/tos-alisg-pve-0037c001/o0I2aHqBzAyz7A9iikql1AIMCAq0fmhwMIE2cm/?a=1988&bti=NDU3ZjAwOg%3D%3D&ch=0&cr=3&dr=0&lr=all&cd=0%7C0%7C0%7C&cv=1&br=320&bt=160&cs=2&ds=6&eid=12800&ft=4fUEKMRh8Zmo0TM83b4jVcUerpWrKsd.&mime_type=video_mp4&qs=11&rc=aTYzOmlnOTdoZzY2NWRnZkBpM3VlNm05cm1ldjMzODczNEBgYmMuMS5jXzAxNWIzXi1iYSMxbzIzMmRjam5gLS1kMTFzcw%3D%3D&btag=e000b8000&expire=1738258491&l=2025012817342557A716FA7108B4677ED2&ply_type=2&policy=2&signature=ee05e6e10bf34ccd1a8b52b6ab367a50&tk=tt_chain_token",
                                "https://v19-webapp-prime.tiktok.com/video/tos/alisg/tos-alisg-pve-0037c001/o0I2aHqBzAyz7A9iikql1AIMCAq0fmhwMIE2cm/?a=1988&bti=NDU3ZjAwOg%3D%3D&ch=0&cr=3&dr=0&lr=all&cd=0%7C0%7C0%7C&cv=1&br=320&bt=160&cs=2&ds=6&eid=12800&ft=4fUEKMRh8Zmo0TM83b4jVcUerpWrKsd.&mime_type=video_mp4&qs=11&rc=aTYzOmlnOTdoZzY2NWRnZkBpM3VlNm05cm1ldjMzODczNEBgYmMuMS5jXzAxNWIzXi1iYSMxbzIzMmRjam5gLS1kMTFzcw%3D%3D&btag=e000b8000&expire=1738258491&l=2025012817342557A716FA7108B4677ED2&ply_type=2&policy=2&signature=ee05e6e10bf34ccd1a8b52b6ab367a50&tk=tt_chain_token",
                                "https://www.tiktok.com/aweme/v1/play/?faid=1988&file_id=ec0daa62e3834d3eb4f61d4f17f0e3cf&is_play_url=1&item_id=7436775132342848786&line=0&ply_type=2&signaturev3=dmlkZW9faWQ7ZmlsZV9pZDtpdGVtX2lkLmMxZjE0NzA0ZTIzNTUxY2EyMzkwNjlhZmE0OWUwYjAx&tk=tt_chain_token&video_id=v14044g50000csqbmjfog65j635brr40"
                            ],
                            "Width": 576
                        },
                        "QualityType": 28
                    },
                    {
                        "Bitrate": 143367,
                        "CodecType": "h264",
                        "GearName": "lowest_540_0",
                        "MVMAF": "\"\"",
                        "PlayAddr": {
                            "DataSize": 431947,
                            "FileCs": "c:0-16870-f746",
                            "FileHash": "f017d884d711e7ac70ee64b7a6b146a7",
                            "Height": 1024,
                            "Uri": "v14044g50000csqbmjfog65j635brr40",
                            "UrlKey": "v14044g50000csqbmjfog65j635brr40_h264_540p_143367",
                            "UrlList": [
                                "https://v16-webapp-prime.tiktok.com/video/tos/alisg/tos-alisg-pve-0037c001/oY7iICA9I4Iqs2lmZfzM0Elqz50uMB3DmGiwAA/?a=1988&bti=NDU3ZjAwOg%3D%3D&ch=0&cr=3&dr=0&lr=all&cd=0%7C0%7C0%7C&cv=1&br=280&bt=140&cs=0&ds=6&ft=4fUEKMRh8Zmo0TM83b4jVcUerpWrKsd.&mime_type=video_mp4&qs=5&rc=OTY3OGY7NWQ4NWloM2dpNUBpM3VlNm05cm1ldjMzODczNEAyNTZhMGE1Xy0xM2AxXi9gYSMxbzIzMmRjam5gLS1kMTFzcw%3D%3D&btag=e000b8000&expire=1738258491&l=2025012817342557A716FA7108B4677ED2&ply_type=2&policy=2&signature=52ea5a9d2a02c49a9804c649c7a189fa&tk=tt_chain_token",
                                "https://v19-webapp-prime.tiktok.com/video/tos/alisg/tos-alisg-pve-0037c001/oY7iICA9I4Iqs2lmZfzM0Elqz50uMB3DmGiwAA/?a=1988&bti=NDU3ZjAwOg%3D%3D&ch=0&cr=3&dr=0&lr=all&cd=0%7C0%7C0%7C&cv=1&br=280&bt=140&cs=0&ds=6&ft=4fUEKMRh8Zmo0TM83b4jVcUerpWrKsd.&mime_type=video_mp4&qs=5&rc=OTY3OGY7NWQ4NWloM2dpNUBpM3VlNm05cm1ldjMzODczNEAyNTZhMGE1Xy0xM2AxXi9gYSMxbzIzMmRjam5gLS1kMTFzcw%3D%3D&btag=e000b8000&expire=1738258491&l=2025012817342557A716FA7108B4677ED2&ply_type=2&policy=2&signature=52ea5a9d2a02c49a9804c649c7a189fa&tk=tt_chain_token",
                                "https://www.tiktok.com/aweme/v1/play/?faid=1988&file_id=c22fad40ce6f4205ba82d83cd5948356&is_play_url=1&item_id=7436775132342848786&line=0&ply_type=2&signaturev3=dmlkZW9faWQ7ZmlsZV9pZDtpdGVtX2lkLmYwYzNmNTViMzEzZDliZjgwNjllOThkNWEwZTM3OTA0&tk=tt_chain_token&video_id=v14044g50000csqbmjfog65j635brr40"
                            ],
                            "Width": 576
                        },
                        "QualityType": 25
                    }
                ],
                "claInfo": {
                    "captionInfos": [
                        {
                            "captionFormat": "webvtt",
                            "claSubtitleID": "7436803447988488977",
                            "expire": "1738258491",
                            "isAutoGen": true,
                            "isOriginalCaption": true,
                            "language": "ara-SA",
                            "languageCode": "ar",
                            "languageID": "34",
                            "subID": "22968915",
                            "subtitleType": "1",
                            "translationType": "0",
                            "url": "https://v16-webapp.tiktok.com/105ef42523976c6a6a6ad7bba3c34d4a/679bb83b/video/tos/alisg/tos-alisg-pv-0037/3a7702b3579c4fd38904666cbef14e04/?a=1988&bti=NDU3ZjAwOg%3D%3D&ch=0&cr=3&dr=0&lr=all&cd=0%7C0%7C0%7C&cv=1&br=15218&bt=7609&cs=0&ds=4&ft=4b~OyMRh8Zmo0TM83b4jVcUerpWrKsd.&mime_type=video_mp4&qs=13&rc=M3VlNm05cm1ldjMzODczNEBpM3VlNm05cm1ldjMzODczNEAxbzIzMmRjam5gLS1kMTFzYSMxbzIzMmRjam5gLS1kMTFzcw%3D%3D&l=2025012817342557A716FA7108B4677ED2&btag=e00078000",
                            "urlList": [
                                "https://v16-webapp.tiktok.com/105ef42523976c6a6a6ad7bba3c34d4a/679bb83b/video/tos/alisg/tos-alisg-pv-0037/3a7702b3579c4fd38904666cbef14e04/?a=1988&bti=NDU3ZjAwOg%3D%3D&ch=0&cr=3&dr=0&lr=all&cd=0%7C0%7C0%7C&cv=1&br=15218&bt=7609&cs=0&ds=4&ft=4b~OyMRh8Zmo0TM83b4jVcUerpWrKsd.&mime_type=video_mp4&qs=13&rc=M3VlNm05cm1ldjMzODczNEBpM3VlNm05cm1ldjMzODczNEAxbzIzMmRjam5gLS1kMTFzYSMxbzIzMmRjam5gLS1kMTFzcw%3D%3D&l=2025012817342557A716FA7108B4677ED2&btag=e00078000",
                                "https://v16-webapp.tiktok.com/105ef42523976c6a6a6ad7bba3c34d4a/679bb83b/video/tos/alisg/tos-alisg-pv-0037/3a7702b3579c4fd38904666cbef14e04/?a=1988&bti=NDU3ZjAwOg%3D%3D&ch=0&cr=3&dr=0&lr=all&cd=0%7C0%7C0%7C&cv=1&br=15218&bt=7609&cs=0&ds=4&ft=4b~OyMRh8Zmo0TM83b4jVcUerpWrKsd.&mime_type=video_mp4&qs=13&rc=M3VlNm05cm1ldjMzODczNEBpM3VlNm05cm1ldjMzODczNEAxbzIzMmRjam5gLS1kMTFzYSMxbzIzMmRjam5gLS1kMTFzcw%3D%3D&l=2025012817342557A716FA7108B4677ED2&btag=e00078000",
                                "https://vas-useast2a.tiktokv.com/tiktok/v1/subtitle/url?aid=1988&format=webvtt&language=ara-SA&sign=fdfa6851c48d9e7935b292e9c2e1db43&version=1%3Awhisper_lid&vid=v14044g50000csqbmjfog65j635brr40"
                            ],
                            "variant": "whisper_lid"
                        },
                        {
                            "captionFormat": "webvtt",
                            "claSubtitleID": "7436808981249002258",
                            "expire": "1738258491",
                            "isAutoGen": true,
                            "isOriginalCaption": false,
                            "language": "eng-US",
                            "languageCode": "en",
                            "languageID": "2",
                            "subID": "-1956723642",
                            "subtitleType": "4",
                            "translationType": "0",
                            "url": "https://v16-webapp.tiktok.com/97489a72b1da4002891f43eba7ba3419/679bb83b/video/tos/alisg/tos-alisg-pv-0037/5bbf3c6e11244c79b6a857036e4dfc03/?a=1988&bti=NDU3ZjAwOg%3D%3D&ch=0&cr=3&dr=0&lr=all&cd=0%7C0%7C0%7C&cv=1&br=15218&bt=7609&cs=0&ds=4&ft=4b~OyMRh8Zmo0TM83b4jVcUerpWrKsd.&mime_type=video_mp4&qs=13&rc=M3VlNm05cm1ldjMzODczNEBpM3VlNm05cm1ldjMzODczNEAxbzIzMmRjam5gLS1kMTFzYSMxbzIzMmRjam5gLS1kMTFzcw%3D%3D&l=2025012817342557A716FA7108B4677ED2&btag=e00078000",
                            "urlList": [
                                "https://v16-webapp.tiktok.com/97489a72b1da4002891f43eba7ba3419/679bb83b/video/tos/alisg/tos-alisg-pv-0037/5bbf3c6e11244c79b6a857036e4dfc03/?a=1988&bti=NDU3ZjAwOg%3D%3D&ch=0&cr=3&dr=0&lr=all&cd=0%7C0%7C0%7C&cv=1&br=15218&bt=7609&cs=0&ds=4&ft=4b~OyMRh8Zmo0TM83b4jVcUerpWrKsd.&mime_type=video_mp4&qs=13&rc=M3VlNm05cm1ldjMzODczNEBpM3VlNm05cm1ldjMzODczNEAxbzIzMmRjam5gLS1kMTFzYSMxbzIzMmRjam5gLS1kMTFzcw%3D%3D&l=2025012817342557A716FA7108B4677ED2&btag=e00078000",
                                "https://v16-webapp.tiktok.com/97489a72b1da4002891f43eba7ba3419/679bb83b/video/tos/alisg/tos-alisg-pv-0037/5bbf3c6e11244c79b6a857036e4dfc03/?a=1988&bti=NDU3ZjAwOg%3D%3D&ch=0&cr=3&dr=0&lr=all&cd=0%7C0%7C0%7C&cv=1&br=15218&bt=7609&cs=0&ds=4&ft=4b~OyMRh8Zmo0TM83b4jVcUerpWrKsd.&mime_type=video_mp4&qs=13&rc=M3VlNm05cm1ldjMzODczNEBpM3VlNm05cm1ldjMzODczNEAxbzIzMmRjam5gLS1kMTFzYSMxbzIzMmRjam5gLS1kMTFzcw%3D%3D&l=2025012817342557A716FA7108B4677ED2&btag=e00078000",
                                "https://vas-useast2a.tiktokv.com/tiktok/v1/subtitle/url?aid=1988&format=webvtt&language=eng-US&sign=c89b02a1c0e414d6af9be746500441c5&version=4&vid=v14044g50000csqbmjfog65j635brr40"
                            ],
                            "variant": "default"
                        }
                    ],
                    "captionsType": 2,
                    "enableAutoCaption": true,
                    "hasOriginalAudio": false,
                    "originalLanguageInfo": {
                        "canTranslateRealTimeNoCheck": true,
                        "language": "ara-SA",
                        "languageCode": "ar",
                        "languageID": "34"
                    }
                },
                "codecType": "h264",
                "cover": "https://p16-sign-sg.tiktokcdn.com/obj/tos-alisg-p-0037/ogEAy2zI0M7B5Aquwmq5lfi1iCAIYAmzQI9M9E?lk3s=b59d6b55&x-expires=1738256400&x-signature=qZfKByYVlHY%2BrYvc8%2BiE1Mynm98%3D&shp=b59d6b55&shcp=-",
                "definition": "540p",
                "downloadAddr": "https://v16-webapp-prime.tiktok.com/video/tos/alisg/tos-alisg-pve-0037c001/ogCqamIwqWAiIilvsFI7zmfMR2B3AABE9Q9zM0/?a=1988&bti=NDU3ZjAwOg%3D%3D&ch=0&cr=3&dr=0&lr=all&cd=0%7C0%7C0%7C&cv=1&br=866&bt=433&cs=0&ds=3&ft=4fUEKMRh8Zmo0TM83b4jVcUerpWrKsd.&mime_type=video_mp4&qs=0&rc=OGQ2OjU8O2c3Mzs6OTUzZ0BpM3VlNm05cm1ldjMzODczNEBeYl40MF42Xl4xMmE0LzIzYSMxbzIzMmRjam5gLS1kMTFzcw%3D%3D&btag=e000b8000&expire=1738258491&l=2025012817342557A716FA7108B4677ED2&ply_type=2&policy=2&signature=29ffb019985f68e82c1e9d7801028b94&tk=tt_chain_token",
                "duration": 24,
                "dynamicCover": "https://p16-sign-sg.tiktokcdn.com/obj/tos-alisg-p-0037/osrMAqfBqIz1I9zCMu9IQm7l0A5Azi2EiA1mIw?lk3s=b59d6b55&x-expires=1738256400&x-signature=SkCIOANJx%2FwXHpOHaiKo8TfvLvk%3D&shp=b59d6b55&shcp=-",
                "encodeUserTag": "",
                "encodedType": "normal",
                "format": "mp4",
                "height": 1024,
                "id": "7436775132342848786",
                "originCover": "https://p16-sign-sg.tiktokcdn.com/obj/tos-alisg-p-0037/oEI80z9CFAls9wIMzqIA4iiA2uBv7mAoMfIm5q?lk3s=b59d6b55&x-expires=1738256400&x-signature=IvMBa7X6wahbN0bCdsZpeNb%2F5HQ%3D&shp=b59d6b55&shcp=-",
                "playAddr": "https://v16-webapp-prime.tiktok.com/video/tos/alisg/tos-alisg-pve-0037c001/oUN8EYCNgtmRAQVznEIRZfFRE7BpULfdB2TQDk/?a=1988&bti=NDU3ZjAwOg%3D%3D&ch=0&cr=3&dr=0&lr=all&cd=0%7C0%7C0%7C&cv=1&br=404&bt=202&cs=0&ds=6&ft=4fUEKMRh8Zmo0TM83b4jVcUerpWrKsd.&mime_type=video_mp4&qs=4&rc=Omg7NGg1ZzVnOTo2ODRmM0BpM3VlNm05cm1ldjMzODczNEAzMGI0NGNfXjAxNDQxY2NiYSMxbzIzMmRjam5gLS1kMTFzcw%3D%3D&btag=e000b8000&expire=1738258491&l=2025012817342557A716FA7108B4677ED2&ply_type=2&policy=2&signature=c59a6e357ae89abbef7eed35120f78a7&tk=tt_chain_token",
                "ratio": "540p",
                "reflowCover": "https://p16-sign-sg.tiktokcdn.com/tos-alisg-p-0037/ogEAy2zI0M7B5Aquwmq5lfi1iCAIYAmzQI9M9E~tplv-photomode-video-cover:480:480.jpeg?lk3s=b59d6b55&x-expires=1738256400&x-signature=lFLK4FdSb9GyIvM7SKBiSFjDRnc%3D&shp=b59d6b55&shcp=-",
                "shareCover": [
                    "",
                    "https://p16-sign-sg.tiktokcdn.com/tos-alisg-p-0037/oEI80z9CFAls9wIMzqIA4iiA2uBv7mAoMfIm5q~tplv-photomode-tiktok-play.jpeg?lk3s=b59d6b55&x-expires=1738688400&x-signature=pJqVNUpPvmkDPIxAvSA3QS6ecHU%3D&shp=b59d6b55&shcp=-",
                    "https://p16-sign-sg.tiktokcdn.com/tos-alisg-p-0037/oEI80z9CFAls9wIMzqIA4iiA2uBv7mAoMfIm5q~tplv-photomode-share-play.jpeg?lk3s=b59d6b55&x-expires=1738688400&x-signature=pCdOD7LVSsT%2Fxkt2KehcPWlTmJM%3D&shp=b59d6b55&shcp=-"
                ],
                "size": 624930,
                "subtitleInfos": [
                    {
                        "Format": "webvtt",
                        "LanguageCodeName": "eng-US",
                        "LanguageID": "2",
                        "Size": 337,
                        "Source": "MT",
                        "Url": "https://v16-webapp.tiktok.com/97489a72b1da4002891f43eba7ba3419/679bb83b/video/tos/alisg/tos-alisg-pv-0037/5bbf3c6e11244c79b6a857036e4dfc03/?a=1988&bti=NDU3ZjAwOg%3D%3D&ch=0&cr=3&dr=0&lr=all&cd=0%7C0%7C0%7C&cv=1&br=15218&bt=7609&cs=0&ds=4&ft=4b~OyMRh8Zmo0TM83b4jVcUerpWrKsd.&mime_type=video_mp4&qs=13&rc=M3VlNm05cm1ldjMzODczNEBpM3VlNm05cm1ldjMzODczNEAxbzIzMmRjam5gLS1kMTFzYSMxbzIzMmRjam5gLS1kMTFzcw%3D%3D&l=2025012817342557A716FA7108B4677ED2&btag=e00078000",
                        "UrlExpire": 1738258491,
                        "Version": "4",
                        "VideoSubtitleID": -1956723642
                    },
                    {
                        "Format": "webvtt",
                        "LanguageCodeName": "ara-SA",
                        "LanguageID": "34",
                        "Size": 634,
                        "Source": "ASR",
                        "Url": "https://v16-webapp.tiktok.com/105ef42523976c6a6a6ad7bba3c34d4a/679bb83b/video/tos/alisg/tos-alisg-pv-0037/3a7702b3579c4fd38904666cbef14e04/?a=1988&bti=NDU3ZjAwOg%3D%3D&ch=0&cr=3&dr=0&lr=all&cd=0%7C0%7C0%7C&cv=1&br=15218&bt=7609&cs=0&ds=4&ft=4b~OyMRh8Zmo0TM83b4jVcUerpWrKsd.&mime_type=video_mp4&qs=13&rc=M3VlNm05cm1ldjMzODczNEBpM3VlNm05cm1ldjMzODczNEAxbzIzMmRjam5gLS1kMTFzYSMxbzIzMmRjam5gLS1kMTFzcw%3D%3D&l=2025012817342557A716FA7108B4677ED2&btag=e00078000",
                        "UrlExpire": 1738258491,
                        "Version": "1:whisper_lid",
                        "VideoSubtitleID": 22968915
                    }
                ],
                "videoQuality": "lower",
                "volumeInfo": {
                    "Loudness": -13,
                    "Peak": 0.63826
                },
                "width": 576,
                "zoomCover": {
                    "240": "https://p16-sign-sg.tiktokcdn.com/tos-alisg-p-0037/ogEAy2zI0M7B5Aquwmq5lfi1iCAIYAmzQI9M9E~tplv-photomode-zoomcover:240:240.avif?lk3s=b59d6b55&x-expires=1738256400&x-signature=fDK%2Fi4D0JFc%2F%2Bn2KJKmPi0rHp1s%3D&shp=b59d6b55&shcp=-",
                    "480": "https://p16-sign-sg.tiktokcdn.com/tos-alisg-p-0037/ogEAy2zI0M7B5Aquwmq5lfi1iCAIYAmzQI9M9E~tplv-photomode-zoomcover:480:480.avif?lk3s=b59d6b55&x-expires=1738256400&x-signature=DaaRvlyrEpasl9CaMAm6FsFfjk4%3D&shp=b59d6b55&shcp=-",
                    "720": "https://p16-sign-sg.tiktokcdn.com/tos-alisg-p-0037/ogEAy2zI0M7B5Aquwmq5lfi1iCAIYAmzQI9M9E~tplv-photomode-zoomcover:720:720.avif?lk3s=b59d6b55&x-expires=1738256400&x-signature=Hnt7qZLslc%2B5Yjnej2hTKntgah4%3D&shp=b59d6b55&shcp=-",
                    "960": "https://p16-sign-sg.tiktokcdn.com/tos-alisg-p-0037/ogEAy2zI0M7B5Aquwmq5lfi1iCAIYAmzQI9M9E~tplv-photomode-zoomcover:960:960.avif?lk3s=b59d6b55&x-expires=1738256400&x-signature=Apc0jcObsxsT5IEBRNYJYFPHGPA%3D&shp=b59d6b55&shcp=-"
                }
            },
            "vl1": false
        }
    ],
    "liveCardDisplay": 0,
    "log_pb": {
        "impr_id": "2025012817342557A716FA7108B4677ED2"
    },
    "statusCode": 0,
    "status_code": 0,
    "status_msg": ""
}